Workbook

Sheet RELATÓRIO DE VENDAS
A1: Cód. | B1: Cliente | C1: CIDADE | D1: UF | E1: LOCALIZAÇÃO | F1: DATA2 | G1: Valor custo | H1: Valor total | I1: MARGEM BRUTA | J1: %MARGEM BRUTA | K1: CLASSIFICAÇÃO | L1: BAIRRO
A2: 3708 | B2: E L FRAGNAN SERRALHERIA E SERVICOS EIRELI | C2: =VLOOKUP(Tabela1[[#This Row],[Cliente]],'BASE DE CLIENTES'!A:E,2,0) -> Brasília | D2: =VLOOKUP(Tabela1[[#This Row],[Cliente]],'BASE DE CLIENTES'!A:C,3,0) -> DF | E2: =CONCATENATE(Tabela1[[#This Row],[CIDADE]],",",Tabela1[[#This Row],[UF]]) -> Brasília,DF | F2: 45688 | G2: 811.63 | H2: 1750 | I2: =Tabela1[[#This Row],[Valor total]]-Tabela1[[#This Row],[Valor custo]] -> 938.37 | J2: =Tabela1[[#This Row],[MARGEM BRUTA]]/Tabela1[[#This Row],[Valor total]] -> 0.53621143 | K2: =VLOOKUP(Tabela1[[#This Row],[Cliente]],'BASE DE CLIENTES'!A:D,4,0) -> EMPRESA COM MAQUINA | L2: =VLOOKUP(Tabela1[[#This Row],[Cliente]],'BASE DE CLIENTES'!A:E,5,0) -> CANDANGOLANDIA
A3: 3707 | B3: 25.157.978 FERNANDA CRISTINA SOUZA DA SILVA | C3: =VLOOKUP(Tabela1[[#This Row],[Cliente]],'BASE DE CLIENTES'!A:E,2,0) -> Brasília | D3: =VLOOKUP(Tabela1[[#This Row],[Cliente]],'BASE DE CLIENTES'!A:C,3,0) -> DF | E3: =CONCATENATE(Tabela1[[#This Row],[CIDADE]],",",Tabela1[[#This Row],[UF]]) -> Brasília,DF | F3: 45688 | G3: 104.4 | H3: 364.6 | I3: =Tabela1[[#This Row],[Valor total]]-Tabela1[[#This Row],[Valor custo]] -> 260.2 | J3: =Tabela1[[#This Row],[MARGEM BRUTA]]/Tabela1[[#This Row],[Valor total]] -> 0.7136588 | K3: =VLOOKUP(Tabela1[[#This Row],[Cliente]],'BASE DE CLIENTES'!A:D,4,0) -> SERRALHEIRO | L3: =VLOOKUP(Tabela1[[#This Row],[Cliente]],'BASE DE CLIENTES'!A:E,5,0) -> SETOR HABITACIONAL VICENTE PIRES
A4: 3675 | B4: RONALDO ADRIANO DA SILVA SOLSA | C4: =VLOOKUP(Tabela1[[#This Row],[Cliente]],'BASE DE CLIENTES'!A:E,2,0) -> Águas Lindas de Goiás | D4: =VLOOKUP(Tabela1[[#This Row],[Cliente]],'BASE DE CLIENTES'!A:C,3,0) -> GO | E4: =CONCATENATE(Tabela1[[#This Row],[CIDADE]],",",Tabela1[[#This Row],[UF]]) -> Águas Lindas de Goiás,GO | F4: 45686 | G4: 514.45 | H4: 805 | I4: =Tabela1[[#This Row],[Valor total]]-Tabela1[[#This Row],[Valor custo]] -> 290.55 | J4: =Tabela1[[#This Row],[MARGEM BRUTA]]/Tabela1[[#This Row],[Valor total]] -> 0.36093168 | K4: =VLOOKUP(Tabela1[[#This Row],[Cliente]],'BASE DE CLIENTES'!A:D,4,0) -> SERRALHEIRO | L4: =VLOOKUP(Tabela1[[#This Row],[Cliente]],'BASE DE CLIENTES'!A:E,5,0) -> Águas Lindas de Goiás
A5: 3661 | B5: MARIO APARECIDO PEREIRA DE BRITO | C5: =VLOOKUP(Tabela1[[#This Row],[Cliente]],'BASE DE CLIENTES'!A:E,2,0) -> Águas Lindas de Goiás | D5: =VLOOKUP(Tabela1[[#This Row],[Cliente]],'BASE DE CLIENTES'!A:C,3,0) -> GO | E5: =CONCATENATE(Tabela1[[#This Row],[CIDADE]],",",Tabela1[[#This Row],[UF]]) -> Águas Lindas de Goiás,GO | F5: 45684 | G5: 25.94 | H5: 40 | I5: =Tabela1[[#This Row],[Valor total]]-Tabela1[[#This Row],[Valor custo]] -> 14.06 | J5: =Tabela1[[#This Row],[MARGEM BRUTA]]/Tabela1[[#This Row],[Valor total]] -> 0.3515 | K5: =VLOOKUP(Tabela1[[#This Row],[Cliente]],'BASE DE CLIENTES'!A:D,4,0) -> SERRALHEIRO | L5: =VLOOKUP(Tabela1[[#This Row],[Cliente]],'BASE DE CLIENTES'!A:E,5,0) -> Águas Lindas de Goiás
B6: CHAVEIRO MARCOS ÁGUAS CLARAS | C6: =VLOOKUP(Tabela1[[#This Row],[Cliente]],'BASE DE CLIENTES'!A:E,2,0) -> Brasília | D6: =VLOOKUP(Tabela1[[#This Row],[Cliente]],'BASE DE CLIENTES'!A:C,3,0) -> DF | E6: =CONCATENATE(Tabela1[[#This Row],[CIDADE]],",",Tabela1[[#This Row],[UF]]) -> Brasília,DF | F6: 45892 | G6: 293.13 | H6: 450 | I6: =Tabela1[[#This Row],[Valor total]]-Tabela1[[#This Row],[Valor custo]] -> 156.87 | J6: =Tabela1[[#This Row],[MARGEM BRUTA]]/Tabela1[[#This Row],[Valor total]] -> 0.3486 | K6: =VLOOKUP(Tabela1[[#This Row],[Cliente]],'BASE DE CLIENTES'!A:D,4,0) -> CHAVEIRO | L6: =VLOOKUP(Tabela1[[#This Row],[Cliente]],'BASE DE CLIENTES'!A:E,5,0) -> NA
B7: DILMAR PEREIRA DE SOUZA | C7: =VLOOKUP(Tabela1[[#This Row],[Cliente]],'BASE DE CLIENTES'!A:E,2,0) -> Brasília | D7: =VLOOKUP(Tabela1[[#This Row],[Cliente]],'BASE DE CLIENTES'!A:C,3,0) -> DF | E7: =CONCATENATE(Tabela1[[#This Row],[CIDADE]],",",Tabela1[[#This Row],[UF]]) -> Brasília,DF | F7: 45736 | G7: 9078.3 | H7: 13375 | I7: =Tabela1[[#This Row],[Valor total]]-Tabela1[[#This Row],[Valor custo]] -> 4296.7 | J7: =Tabela1[[#This Row],[MARGEM BRUTA]]/Tabela1[[#This Row],[Valor total]] -> 0.3212486 | K7: =VLOOKUP(Tabela1[[#This Row],[Cliente]],'BASE DE CLIENTES'!A:D,4,0) -> EMPRESA COM MAQUINA | L7: =VLOOKUP(Tabela1[[#This Row],[Cliente]],'BASE DE CLIENTES'!A:E,5,0) -> RIACHO FUNDO II
A8: 3702 | B8: ACOFER METALURGICA E COMERCIO LTDA | C8: =VLOOKUP(Tabela1[[#This Row],[Cliente]],'BASE DE CLIENTES'!A:E,2,0) -> Brasília | D8: =VLOOKUP(Tabela1[[#This Row],[Cliente]],'BASE DE CLIENTES'!A:C,3,0) -> DF | E8: =CONCATENATE(Tabela1[[#This Row],[CIDADE]],",",Tabela1[[#This Row],[UF]]) -> Brasília,DF | F8: 45688 | G8: 878.4 | H8: 1320 | I8: =Tabela1[[#This Row],[Valor total]]-Tabela1[[#This Row],[Valor custo]] -> 441.6 | J8: =Tabela1[[#This Row],[MARGEM BRUTA]]/Tabela1[[#This Row],[Valor total]] -> 0.33454545 | K8: =VLOOKUP(Tabela1[[#This Row],[Cliente]],'BASE DE CLIENTES'!A:D,4,0) -> EMPRESA SEM MAQUINA | L8: =VLOOKUP(Tabela1[[#This Row],[Cliente]],'BASE DE CLIENTES'!A:E,5,0) -> SETOR INDUSTRIAL (TAGUATINGA)
A9: 3701 | B9: CENTRAL PORTAS DE ACO AUTOMATICAS LTDA | C9: =VLOOKUP(Tabela1[[#This Row],[Cliente]],'BASE DE CLIENTES'!A:E,2,0) -> Brasília | D9: =VLOOKUP(Tabela1[[#This Row],[Cliente]],'BASE DE CLIENTES'!A:C,3,0) -> DF | E9: =CONCATENATE(Tabela1[[#This Row],[CIDADE]],",",Tabela1[[#This Row],[UF]]) -> Brasília,DF | F9: 45688 | G9: 39.87 | H9: 60 | I9: =Tabela1[[#This Row],[Valor total]]-Tabela1[[#This Row],[Valor custo]] -> 20.13 | J9: =Tabela1[[#This Row],[MARGEM BRUTA]]/Tabela1[[#This Row],[Valor total]] -> 0.3355 | K9: =VLOOKUP(Tabela1[[#This Row],[Cliente]],'BASE DE CLIENTES'!A:D,4,0) -> EMPRESA COM MAQUINA | L9: =VLOOKUP(Tabela1[[#This Row],[Cliente]],'BASE DE CLIENTES'!A:E,5,0) -> CEILANDIA NORTE (CEILANDIA)
A10: 3700 | B10: 34.505.918 JOSE ANTONIO DUTRA DA SILVA | C10: =VLOOKUP(Tabela1[[#This Row],[Cliente]],'BASE DE CLIENTES'!A:E,2,0) -> Brasília | D10: =VLOOKUP(Tabela1[[#This Row],[Cliente]],'BASE DE CLIENTES'!A:C,3,0) -> DF | E10: =CONCATENATE(Tabela1[[#This Row],[CIDADE]],",",Tabela1[[#This Row],[UF]]) -> Brasília,DF | F10: 45688 | G10: 857.96 | H10: 1700 | I10: =Tabela1[[#This Row],[Valor total]]-Tabela1[[#This Row],[Valor custo]] -> 842.04 | J10: =Tabela1[[#This Row],[MARGEM BRUTA]]/Tabela1[[#This Row],[Valor total]] -> 0.49531765 | K10: =VLOOKUP(Tabela1[[#This Row],[Cliente]],'BASE DE CLIENTES'!A:D,4,0) -> EMPRESA SEM MAQUINA | L10: =VLOOKUP(Tabela1[[#This Row],[Cliente]],'BASE DE CLIENTES'!A:E,5,0) -> RECANTO DAS EMAS
A11: 3699 | B11: CENTRAL PORTAS DE ACO AUTOMATICAS LTDA | C11: =VLOOKUP(Tabela1[[#This Row],[Cliente]],'BASE DE CLIENTES'!A:E,2,0) -> Brasília | D11: =VLOOKUP(Tabela1[[#This Row],[Cliente]],'BASE DE CLIENTES'!A:C,3,0) -> DF | E11: =CONCATENATE(Tabela1[[#This Row],[CIDADE]],",",Tabela1[[#This Row],[UF]]) -> Brasília,DF | F11: 45688 | G11: 1764.47 | H11: 2855 | I11: =Tabela1[[#This Row],[Valor total]]-Tabela1[[#This Row],[Valor custo]] -> 1090.53 | J11: =Tabela1[[#This Row],[MARGEM BRUTA]]/Tabela1[[#This Row],[Valor total]] -> 0.38197198 | K11: =VLOOKUP(Tabela1[[#This Row],[Cliente]],'BASE DE CLIENTES'!A:D,4,0) -> EMPRESA COM MAQUINA | L11: =VLOOKUP(Tabela1[[#This Row],[Cliente]],'BASE DE CLIENTES'!A:E,5,0) -> CEILANDIA NORTE (CEILANDIA)
A12: 3657 | B12: Gefferson de Amorim | C12: =VLOOKUP(Tabela1[[#This Row],[Cliente]],'BASE DE CLIENTES'!A:E,2,0) -> Águas Lindas de Goiás | D12: =VLOOKUP(Tabela1[[#This Row],[Cliente]],'BASE DE CLIENTES'!A:C,3,0) -> GO | E12: =CONCATENATE(Tabela1[[#This Row],[CIDADE]],",",Tabela1[[#This Row],[UF]]) -> Águas Lindas de Goiás,GO | F12: 45684 | G12: 1187.66 | H12: 2050 | I12: =Tabela1[[#This Row],[Valor total]]-Tabela1[[#This Row],[Valor custo]] -> 862.34 | J12: =Tabela1[[#This Row],[MARGEM BRUTA]]/Tabela1[[#This Row],[Valor total]] -> 0.42065366 | K12: =VLOOKUP(Tabela1[[#This Row],[Cliente]],'BASE DE CLIENTES'!A:D,4,0) -> SERRALHEIRO | L12: =VLOOKUP(Tabela1[[#This Row],[Cliente]],'BASE DE CLIENTES'!A:E,5,0) -> Águas Lindas de Goiás
A13: 3644 | B13: RONALDO ADRIANO DA SILVA SOLSA | C13: =VLOOKUP(Tabela1[[#This Row],[Cliente]],'BASE DE CLIENTES'!A:E,2,0) -> Águas Lindas de Goiás | D13: =VLOOKUP(Tabela1[[#This Row],[Cliente]],'BASE DE CLIENTES'!A:C,3,0) -> GO | E13: =CONCATENATE(Tabela1[[#This Row],[CIDADE]],",",Tabela1[[#This Row],[UF]]) -> Águas Lindas de Goiás,GO | F13: 45681 | G13: 1317.6 | H13: 1935 | I13: =Tabela1[[#This Row],[Valor total]]-Tabela1[[#This Row],[Valor custo]] -> 617.4 | J13: =Tabela1[[#This Row],[MARGEM BRUTA]]/Tabela1[[#This Row],[Valor total]] -> 0.31906977 | K13: =VLOOKUP(Tabela1[[#This Row],[Cliente]],'BASE DE CLIENTES'!A:D,4,0) -> SERRALHEIRO | L13: =VLOOKUP(Tabela1[[#This Row],[Cliente]],'BASE DE CLIENTES'!A:E,5,0) -> Águas Lindas de Goiás
A14: 3631 | B14: Gefferson de Amorim | C14: =VLOOKUP(Tabela1[[#This Row],[Cliente]],'BASE DE CLIENTES'!A:E,2,0) -> Águas Lindas de Goiás | D14: =VLOOKUP(Tabela1[[#This Row],[Cliente]],'BASE DE CLIENTES'!A:C,3,0) -> GO | E14: =CONCATENATE(Tabela1[[#This Row],[CIDADE]],",",Tabela1[[#This Row],[UF]]) -> Águas Lindas de Goiás,GO | F14: 45680 | G14: 514.45 | H14: 720 | I14: =Tabela1[[#This Row],[Valor total]]-Tabela1[[#This Row],[Valor custo]] -> 205.55 | J14: =Tabela1[[#This Row],[MARGEM BRUTA]]/Tabela1[[#This Row],[Valor total]] -> 0.28548611 | K14: =VLOOKUP(Tabela1[[#This Row],[Cliente]],'BASE DE CLIENTES'!A:D,4,0) -> SERRALHEIRO | L14: =VLOOKUP(Tabela1[[#This Row],[Cliente]],'BASE DE CLIENTES'!A:E,5,0) -> Águas Lindas de Goiás
B15: Gefferson de Amorim | C15: =VLOOKUP(Tabela1[[#This Row],[Cliente]],'BASE DE CLIENTES'!A:E,2,0) -> Águas Lindas de Goiás | D15: =VLOOKUP(Tabela1[[#This Row],[Cliente]],'BASE DE CLIENTES'!A:C,3,0) -> GO | E15: =CONCATENATE(Tabela1[[#This Row],[CIDADE]],",",Tabela1[[#This Row],[UF]]) -> Águas Lindas de Goiás,GO | F15: 45678 | G15: 439.2 | H15: 645 | I15: =Tabela1[[#This Row],[Valor total]]-Tabela1[[#This Row],[Valor custo]] -> 205.8 | J15: =Tabela1[[#This Row],[MARGEM BRUTA]]/Tabela1[[#This Row],[Valor total]] -> 0.31906977 | K15: =VLOOKUP(Tabela1[[#This Row],[Cliente]],'BASE DE CLIENTES'!A:D,4,0) -> SERRALHEIRO | L15: =VLOOKUP(Tabela1[[#This Row],[Cliente]],'BASE DE CLIENTES'!A:E,5,0) -> Águas Lindas de Goiás
B16: MARIO APARECIDO PEREIRA DE BRITO | C16: =VLOOKUP(Tabela1[[#This Row],[Cliente]],'BASE DE CLIENTES'!A:E,2,0) -> Águas Lindas de Goiás | D16: =VLOOKUP(Tabela1[[#This Row],[Cliente]],'BASE DE CLIENTES'!A:C,3,0) -> GO | E16: =CONCATENATE(Tabela1[[#This Row],[CIDADE]],",",Tabela1[[#This Row],[UF]]) -> Águas Lindas de Goiás,GO | F16: 45673 | G16: 20.88 | H16: 90 | I16: =Tabela1[[#This Row],[Valor total]]-Tabela1[[#This Row],[Valor custo]] -> 69.12 | J16: =Tabela1[[#This Row],[MARGEM BRUTA]]/Tabela1[[#This Row],[Valor total]] -> 0.768 | K16: =VLOOKUP(Tabela1[[#This Row],[Cliente]],'BASE DE CLIENTES'!A:D,4,0) -> SERRALHEIRO | L16: =VLOOKUP(Tabela1[[#This Row],[Cliente]],'BASE DE CLIENTES'!A:E,5,0) -> Águas Lindas de Goiás
A17: 3693 | B17: 19.488.372 EZEQUIEL DE FREITAS CARNEIRO | C17: =VLOOKUP(Tabela1[[#This Row],[Cliente]],'BASE DE CLIENTES'!A:E,2,0) -> Brasília | D17: =VLOOKUP(Tabela1[[#This Row],[Cliente]],'BASE DE CLIENTES'!A:C,3,0) -> DF | E17: =CONCATENATE(Tabela1[[#This Row],[CIDADE]],",",Tabela1[[#This Row],[UF]]) -> Brasília,DF | F17: 45688 | G17: 514.45 | H17: 741.6 | I17: =Tabela1[[#This Row],[Valor total]]-Tabela1[[#This Row],[Valor custo]] -> 227.15 | J17: =Tabela1[[#This Row],[MARGEM BRUTA]]/Tabela1[[#This Row],[Valor total]] -> 0.3062972 | K17: =VLOOKUP(Tabela1[[#This Row],[Cliente]],'BASE DE CLIENTES'!A:D,4,0) -> SERRALHEIRO | L17: =VLOOKUP(Tabela1[[#This Row],[Cliente]],'BASE DE CLIENTES'!A:E,5,0) -> RECANTO DAS EMAS
A18: 3692 | B18: WILSON JOSE RODRIGUES JUNIOR 69748209172 | C18: =VLOOKUP(Tabela1[[#This Row],[Cliente]],'BASE DE CLIENTES'!A:E,2,0) -> Brasília | D18: =VLOOKUP(Tabela1[[#This Row],[Cliente]],'BASE DE CLIENTES'!A:C,3,0) -> DF | E18: =CONCATENATE(Tabela1[[#This Row],[CIDADE]],",",Tabela1[[#This Row],[UF]]) -> Brasília,DF | F18: 45688 | G18: 514.45 | H18: 720 | I18: =Tabela1[[#This Row],[Valor total]]-Tabela1[[#This Row],[Valor custo]] -> 205.55 | J18: =Tabela1[[#This Row],[MARGEM BRUTA]]/Tabela1[[#This Row],[Valor total]] -> 0.28548611 | K18: =VLOOKUP(Tabela1[[#This Row],[Cliente]],'BASE DE CLIENTES'!A:D,4,0) -> SERRALHEIRO | L18: =VLOOKUP(Tabela1[[#This Row],[Cliente]],'BASE DE CLIENTES'!A:E,5,0) -> CEILANDIA SUL (CEILANDIA)
A19: 3691 | B19: EDIVALDO FERNANDES DA SILVA 00098636138 | C19: =VLOOKUP(Tabela1[[#This Row],[Cliente]],'BASE DE CLIENTES'!A:E,2,0) -> Brasília | D19: =VLOOKUP(Tabela1[[#This Row],[Cliente]],'BASE DE CLIENTES'!A:C,3,0) -> DF | E19: =CONCATENATE(Tabela1[[#This Row],[CIDADE]],",",Tabela1[[#This Row],[UF]]) -> Brasília,DF | F19: 45688 | G19: 77.82 | H19: 108 | I19: =Tabela1[[#This Row],[Valor total]]-Tabela1[[#This Row],[Valor custo]] -> 30.18 | J19: =Tabela1[[#This Row],[MARGEM BRUTA]]/Tabela1[[#This Row],[Valor total]] -> 0.27944444 | K19: =VLOOKUP(Tabela1[[#This Row],[Cliente]],'BASE DE CLIENTES'!A:D,4,0) -> EMPRESA SEM MAQUINA | L19: =VLOOKUP(Tabela1[[#This Row],[Cliente]],'BASE DE CLIENTES'!A:E,5,0) -> PONTE ALTA NORTE (GAMA)
A20: 3690 | B20: EDIVALDO FERNANDES DA SILVA 00098636138 | C20: =VLOOKUP(Tabela1[[#This Row],[Cliente]],'BASE DE CLIENTES'!A:E,2,0) -> Brasília | D20: =VLOOKUP(Tabela1[[#This Row],[Cliente]],'BASE DE CLIENTES'!A:C,3,0) -> DF | E20: =CONCATENATE(Tabela1[[#This Row],[CIDADE]],",",Tabela1[[#This Row],[UF]]) -> Brasília,DF | F20: 45688 | G20: 62.75 | H20: 70 | I20: =Tabela1[[#This Row],[Valor total]]-Tabela1[[#This Row],[Valor custo]] -> 7.25 | J20: =Tabela1[[#This Row],[MARGEM BRUTA]]/Tabela1[[#This Row],[Valor total]] -> 0.10357143 | K20: =VLOOKUP(Tabela1[[#This Row],[Cliente]],'BASE DE CLIENTES'!A:D,4,0) -> EMPRESA SEM MAQUINA | L20: =VLOOKUP(Tabela1[[#This Row],[Cliente]],'BASE DE CLIENTES'!A:E,5,0) -> PONTE ALTA NORTE (GAMA)
A21: 3688 | B21: EDIVALDO FERNANDES DA SILVA 00098636138 | C21: =VLOOKUP(Tabela1[[#This Row],[Cliente]],'BASE DE CLIENTES'!A:E,2,0) -> Brasília | D21: =VLOOKUP(Tabela1[[#This Row],[Cliente]],'BASE DE CLIENTES'!A:C,3,0) -> DF | E21: =CONCATENATE(Tabela1[[#This Row],[CIDADE]],",",Tabela1[[#This Row],[UF]]) -> Brasília,DF | F21: 45688 | G21: 718.57 | H21: 1250 | I21: =Tabela1[[#This Row],[Valor total]]-Tabela1[[#This Row],[Valor custo]] -> 531.43 | J21: =Tabela1[[#This Row],[MARGEM BRUTA]]/Tabela1[[#This Row],[Valor total]] -> 0.425144 | K21: =VLOOKUP(Tabela1[[#This Row],[Cliente]],'BASE DE CLIENTES'!A:D,4,0) -> EMPRESA SEM MAQUINA | L21: =VLOOKUP(Tabela1[[#This Row],[Cliente]],'BASE DE CLIENTES'!A:E,5,0) -> PONTE ALTA NORTE (GAMA)
B22: MARIO APARECIDO PEREIRA DE BRITO | C22: =VLOOKUP(Tabela1[[#This Row],[Cliente]],'BASE DE CLIENTES'!A:E,2,0) -> Águas Lindas de Goiás | D22: =VLOOKUP(Tabela1[[#This Row],[Cliente]],'BASE DE CLIENTES'!A:C,3,0) -> GO | E22: =CONCATENATE(Tabela1[[#This Row],[CIDADE]],",",Tabela1[[#This Row],[UF]]) -> Águas Lindas de Goiás,GO | F22: 45671 | G22: 1594.35 | H22: 2355 | I22: =Tabela1[[#This Row],[Valor total]]-Tabela1[[#This Row],[Valor custo]] -> 760.65 | J22: =Tabela1[[#This Row],[MARGEM BRUTA]]/Tabela1[[#This Row],[Valor total]] -> 0.32299363 | K22: =VLOOKUP(Tabela1[[#This Row],[Cliente]],'BASE DE CLIENTES'!A:D,4,0) -> SERRALHEIRO | L22: =VLOOKUP(Tabela1[[#This Row],[Cliente]],'BASE DE CLIENTES'!A:E,5,0) -> Águas Lindas de Goiás
A23: 3686 | B23: JM PORTAS AUTOMATICAS LTDA | C23: =VLOOKUP(Tabela1[[#This Row],[Cliente]],'BASE DE CLIENTES'!A:E,2,0) -> Brasília | D23: =VLOOKUP(Tabela1[[#This Row],[Cliente]],'BASE DE CLIENTES'!A:C,3,0) -> DF | E23: =CONCATENATE(Tabela1[[#This Row],[CIDADE]],",",Tabela1[[#This Row],[UF]]) -> Brasília,DF | F23: 45688 | G23: 543.6 | H23: 970 | I23: =Tabela1[[#This Row],[Valor total]]-Tabela1[[#This Row],[Valor custo]] -> 426.4 | J23: =Tabela1[[#This Row],[MARGEM BRUTA]]/Tabela1[[#This Row],[Valor total]] -> 0.43958763 | K23: =VLOOKUP(Tabela1[[#This Row],[Cliente]],'BASE DE CLIENTES'!A:D,4,0) -> EMPRESA SEM MAQUINA | L23: =VLOOKUP(Tabela1[[#This Row],[Cliente]],'BASE DE CLIENTES'!A:E,5,0) -> SAMAMBAIA
A24: 3685 | B24: JAIME FRANCISCO SOARES 27103323100 | C24: =VLOOKUP(Tabela1[[#This Row],[Cliente]],'BASE DE CLIENTES'!A:E,2,0) -> Brasília | D24: =VLOOKUP(Tabela1[[#This Row],[Cliente]],'BASE DE CLIENTES'!A:C,3,0) -> DF | E24: =CONCATENATE(Tabela1[[#This Row],[CIDADE]],",",Tabela1[[#This Row],[UF]]) -> Brasília,DF | F24: 45687 | G24: 52.2 | H24: 185 | I24: =Tabela1[[#This Row],[Valor total]]-Tabela1[[#This Row],[Valor custo]] -> 132.8 | J24: =Tabela1[[#This Row],[MARGEM BRUTA]]/Tabela1[[#This Row],[Valor total]] -> 0.71783784 | K24: =VLOOKUP(Tabela1[[#This Row],[Cliente]],'BASE DE CLIENTES'!A:D,4,0) -> EMPRESA SEM MAQUINA | L24: =VLOOKUP(Tabela1[[#This Row],[Cliente]],'BASE DE CLIENTES'!A:E,5,0) -> SETOR HABITACIONAL VICENTE PIRES
A25: 3684 | B25: 34.505.918 JOSE ANTONIO DUTRA DA SILVA | C25: =VLOOKUP(Tabela1[[#This Row],[Cliente]],'BASE DE CLIENTES'!A:E,2,0) -> Brasília | D25: =VLOOKUP(Tabela1[[#This Row],[Cliente]],'BASE DE CLIENTES'!A:C,3,0) -> DF | E25: =CONCATENATE(Tabela1[[#This Row],[CIDADE]],",",Tabela1[[#This Row],[UF]]) -> Brasília,DF | F25: 45687 | G25: 903.4 | H25: 1270 | I25: =Tabela1[[#This Row],[Valor total]]-Tabela1[[#This Row],[Valor custo]] -> 366.6 | J25: =Tabela1[[#This Row],[MARGEM BRUTA]]/Tabela1[[#This Row],[Valor total]] -> 0.28866142 | K25: =VLOOKUP(Tabela1[[#This Row],[Cliente]],'BASE DE CLIENTES'!A:D,4,0) -> EMPRESA SEM MAQUINA | L25: =VLOOKUP(Tabela1[[#This Row],[Cliente]],'BASE DE CLIENTES'!A:E,5,0) -> RECANTO DAS EMAS
A26: 3683 | B26: CENTRAL PORTAS DE ACO AUTOMATICAS LTDA | C26: =VLOOKUP(Tabela1[[#This Row],[Cliente]],'BASE DE CLIENTES'!A:E,2,0) -> Brasília | D26: =VLOOKUP(Tabela1[[#This Row],[Cliente]],'BASE DE CLIENTES'!A:C,3,0) -> DF | E26: =CONCATENATE(Tabela1[[#This Row],[CIDADE]],",",Tabela1[[#This Row],[UF]]) -> Brasília,DF | F26: 45687 | G26: 514.45 | H26: 720 | I26: =Tabela1[[#This Row],[Valor total]]-Tabela1[[#This Row],[Valor custo]] -> 205.55 | J26: =Tabela1[[#This Row],[MARGEM BRUTA]]/Tabela1[[#This Row],[Valor total]] -> 0.28548611 | K26: =VLOOKUP(Tabela1[[#This Row],[Cliente]],'BASE DE CLIENTES'!A:D,4,0) -> EMPRESA COM MAQUINA | L26: =VLOOKUP(Tabela1[[#This Row],[Cliente]],'BASE DE CLIENTES'!A:E,5,0) -> CEILANDIA NORTE (CEILANDIA)
A27: 3682 | B27: ACOFER METALURGICA E COMERCIO LTDA | C27: =VLOOKUP(Tabela1[[#This Row],[Cliente]],'BASE DE CLIENTES'!A:E,2,0) -> Brasília | D27: =VLOOKUP(Tabela1[[#This Row],[Cliente]],'BASE DE CLIENTES'!A:C,3,0) -> DF | E27: =CONCATENATE(Tabela1[[#This Row],[CIDADE]],",",Tabela1[[#This Row],[UF]]) -> Brasília,DF | F27: 45687 | G27: 514.45 | H27: 757 | I27: =Tabela1[[#This Row],[Valor total]]-Tabela1[[#This Row],[Valor custo]] -> 242.55 | J27: =Tabela1[[#This Row],[MARGEM BRUTA]]/Tabela1[[#This Row],[Valor total]] -> 0.32040951 | K27: =VLOOKUP(Tabela1[[#This Row],[Cliente]],'BASE DE CLIENTES'!A:D,4,0) -> EMPRESA SEM MAQUINA | L27: =VLOOKUP(Tabela1[[#This Row],[Cliente]],'BASE DE CLIENTES'!A:E,5,0) -> SETOR INDUSTRIAL (TAGUATINGA)
B28: DILMAR PEREIRA DE SOUZA | C28: =VLOOKUP(Tabela1[[#This Row],[Cliente]],'BASE DE CLIENTES'!A:E,2,0) -> Brasília | D28: =VLOOKUP(Tabela1[[#This Row],[Cliente]],'BASE DE CLIENTES'!A:C,3,0) -> DF | E28: =CONCATENATE(Tabela1[[#This Row],[CIDADE]],",",Tabela1[[#This Row],[UF]]) -> Brasília,DF | F28: 45674 | G28: 8607.27 | H28: 11600 | I28: =Tabela1[[#This Row],[Valor total]]-Tabela1[[#This Row],[Valor custo]] -> 2992.73 | J28: =Tabela1[[#This Row],[MARGEM BRUTA]]/Tabela1[[#This Row],[Valor total]] -> 0.25799397 | K28: =VLOOKUP(Tabela1[[#This Row],[Cliente]],'BASE DE CLIENTES'!A:D,4,0) -> EMPRESA COM MAQUINA | L28: =VLOOKUP(Tabela1[[#This Row],[Cliente]],'BASE DE CLIENTES'!A:E,5,0) -> RIACHO FUNDO II
A29: 3680 | B29: METALURGICA VARELA LTDA | C29: =VLOOKUP(Tabela1[[#This Row],[Cliente]],'BASE DE CLIENTES'!A:E,2,0) -> Brasília | D29: =VLOOKUP(Tabela1[[#This Row],[Cliente]],'BASE DE CLIENTES'!A:C,3,0) -> DF | E29: =CONCATENATE(Tabela1[[#This Row],[CIDADE]],",",Tabela1[[#This Row],[UF]]) -> Brasília,DF | F29: 45687 | G29: 122.74 | H29: 150 | I29: =Tabela1[[#This Row],[Valor total]]-Tabela1[[#This Row],[Valor custo]] -> 27.26 | J29: =Tabela1[[#This Row],[MARGEM BRUTA]]/Tabela1[[#This Row],[Valor total]] -> 0.18173333 | K29: =VLOOKUP(Tabela1[[#This Row],[Cliente]],'BASE DE CLIENTES'!A:D,4,0) -> EMPRESA COM MAQUINA | L29: =VLOOKUP(Tabela1[[#This Row],[Cliente]],'BASE DE CLIENTES'!A:E,5,0) -> TAGUATINGA
A30: 3679 | B30: JAIME FRANCISCO SOARES 27103323100 | C30: =VLOOKUP(Tabela1[[#This Row],[Cliente]],'BASE DE CLIENTES'!A:E,2,0) -> Brasília | D30: =VLOOKUP(Tabela1[[#This Row],[Cliente]],'BASE DE CLIENTES'!A:C,3,0) -> DF | E30: =CONCATENATE(Tabela1[[#This Row],[CIDADE]],",",Tabela1[[#This Row],[UF]]) -> Brasília,DF | F30: 45686 | G30: 268.46 | H30: 550 | I30: =Tabela1[[#This Row],[Valor total]]-Tabela1[[#This Row],[Valor custo]] -> 281.54 | J30: =Tabela1[[#This Row],[MARGEM BRUTA]]/Tabela1[[#This Row],[Valor total]] -> 0.51189091 | K30: =VLOOKUP(Tabela1[[#This Row],[Cliente]],'BASE DE CLIENTES'!A:D,4,0) -> EMPRESA SEM MAQUINA | L30: =VLOOKUP(Tabela1[[#This Row],[Cliente]],'BASE DE CLIENTES'!A:E,5,0) -> SETOR HABITACIONAL VICENTE PIRES
A31: 3678 | B31: FABIO BERNARDO DE ABREU | C31: =VLOOKUP(Tabela1[[#This Row],[Cliente]],'BASE DE CLIENTES'!A:E,2,0) -> Brasília | D31: =VLOOKUP(Tabela1[[#This Row],[Cliente]],'BASE DE CLIENTES'!A:C,3,0) -> DF | E31: =CONCATENATE(Tabela1[[#This Row],[CIDADE]],",",Tabela1[[#This Row],[UF]]) -> Brasília,DF | F31: 45686 | G31: 1543.35 | H31: 2160 | I31: =Tabela1[[#This Row],[Valor total]]-Tabela1[[#This Row],[Valor custo]] -> 616.65 | J31: =Tabela1[[#This Row],[MARGEM BRUTA]]/Tabela1[[#This Row],[Valor total]] -> 0.28548611 | K31: =VLOOKUP(Tabela1[[#This Row],[Cliente]],'BASE DE CLIENTES'!A:D,4,0) -> SERRALHEIRO | L31: =VLOOKUP(Tabela1[[#This Row],[Cliente]],'BASE DE CLIENTES'!A:E,5,0) -> Ceilândia Sul (Ceilândia)
A32: 3677 | B32: JM PORTAS AUTOMATICAS LTDA | C32: =VLOOKUP(Tabela1[[#This Row],[Cliente]],'BASE DE CLIENTES'!A:E,2,0) -> Brasília | D32: =VLOOKUP(Tabela1[[#This Row],[Cliente]],'BASE DE CLIENTES'!A:C,3,0) -> DF | E32: =CONCATENATE(Tabela1[[#This Row],[CIDADE]],",",Tabela1[[#This Row],[UF]]) -> Brasília,DF | F32: 45686 | G32: 439.2 | H32: 620 | I32: =Tabela1[[#This Row],[Valor total]]-Tabela1[[#This Row],[Valor custo]] -> 180.8 | J32: =Tabela1[[#This Row],[MARGEM BRUTA]]/Tabela1[[#This Row],[Valor total]] -> 0.2916129 | K32: =VLOOKUP(Tabela1[[#This Row],[Cliente]],'BASE DE CLIENTES'!A:D,4,0) -> EMPRESA SEM MAQUINA | L32: =VLOOKUP(Tabela1[[#This Row],[Cliente]],'BASE DE CLIENTES'!A:E,5,0) -> SAMAMBAIA
A33: 3676 | B33: FRANCISCO VALDINAR PEREIRA DA SILVA 02490980327 | C33: =VLOOKUP(Tabela1[[#This Row],[Cliente]],'BASE DE CLIENTES'!A:E,2,0) -> Brasília | D33: =VLOOKUP(Tabela1[[#This Row],[Cliente]],'BASE DE CLIENTES'!A:C,3,0) -> DF | E33: =CONCATENATE(Tabela1[[#This Row],[CIDADE]],",",Tabela1[[#This Row],[UF]]) -> Brasília,DF | F33: 45686 | G33: 707.23 | H33: 1450 | I33: =Tabela1[[#This Row],[Valor total]]-Tabela1[[#This Row],[Valor custo]] -> 742.77 | J33: =Tabela1[[#This Row],[MARGEM BRUTA]]/Tabela1[[#This Row],[Valor total]] -> 0.51225517 | K33: =VLOOKUP(Tabela1[[#This Row],[Cliente]],'BASE DE CLIENTES'!A:D,4,0) -> EMPRESA SEM MAQUINA | L33: =VLOOKUP(Tabela1[[#This Row],[Cliente]],'BASE DE CLIENTES'!A:E,5,0) -> RECANTO DAS EMAS
B34: RONALDO ADRIANO DA SILVA SOLSA | C34: =VLOOKUP(Tabela1[[#This Row],[Cliente]],'BASE DE CLIENTES'!A:E,2,0) -> Águas Lindas de Goiás | D34: =VLOOKUP(Tabela1[[#This Row],[Cliente]],'BASE DE CLIENTES'!A:C,3,0) -> GO | E34: =CONCATENATE(Tabela1[[#This Row],[CIDADE]],",",Tabela1[[#This Row],[UF]]) -> Águas Lindas de Goiás,GO | F34: 45671 | G34: 122.74 | H34: 170 | I34: =Tabela1[[#This Row],[Valor total]]-Tabela1[[#This Row],[Valor custo]] -> 47.26 | J34: =Tabela1[[#This Row],[MARGEM BRUTA]]/Tabela1[[#This Row],[Valor total]] -> 0.278 | K34: =VLOOKUP(Tabela1[[#This Row],[Cliente]],'BASE DE CLIENTES'!A:D,4,0) -> SERRALHEIRO | L34: =VLOOKUP(Tabela1[[#This Row],[Cliente]],'BASE DE CLIENTES'!A:E,5,0) -> Águas Lindas de Goiás
A35: 3674 | B35: RAIMUNDO NONATO DA CUNHA 89072898168 | C35: =VLOOKUP(Tabela1[[#This Row],[Cliente]],'BASE DE CLIENTES'!A:E,2,0) -> Brasília | D35: =VLOOKUP(Tabela1[[#This Row],[Cliente]],'BASE DE CLIENTES'!A:C,3,0) -> DF | E35: =CONCATENATE(Tabela1[[#This Row],[CIDADE]],",",Tabela1[[#This Row],[UF]]) -> Brasília,DF | F35: 45686 | G35: 1078.65 | H35: 1585.96 | I35: =Tabela1[[#This Row],[Valor total]]-Tabela1[[#This Row],[Valor custo]] -> 507.31 | J35: =Tabela1[[#This Row],[MARGEM BRUTA]]/Tabela1[[#This Row],[Valor total]] -> 0.31987566 | K35: =VLOOKUP(Tabela1[[#This Row],[Cliente]],'BASE DE CLIENTES'!A:D,4,0) -> SERRALHEIRO | L35: =VLOOKUP(Tabela1[[#This Row],[Cliente]],'BASE DE CLIENTES'!A:E,5,0) -> ARAPOANGA (PLANALTINA)
A36: 3673 | B36: PORTAS DE ACO TROPICAL LTDA | C36: =VLOOKUP(Tabela1[[#This Row],[Cliente]],'BASE DE CLIENTES'!A:E,2,0) -> Brasília | D36: =VLOOKUP(Tabela1[[#This Row],[Cliente]],'BASE DE CLIENTES'!A:C,3,0) -> DF | E36: =CONCATENATE(Tabela1[[#This Row],[CIDADE]],",",Tabela1[[#This Row],[UF]]) -> Brasília,DF | F36: 45686 | G36: 11880.42 | H36: 16400 | I36: =Tabela1[[#This Row],[Valor total]]-Tabela1[[#This Row],[Valor custo]] -> 4519.58 | J36: =Tabela1[[#This Row],[MARGEM BRUTA]]/Tabela1[[#This Row],[Valor total]] -> 0.27558415 | K36: =VLOOKUP(Tabela1[[#This Row],[Cliente]],'BASE DE CLIENTES'!A:D,4,0) -> EMPRESA COM MAQUINA | L36: =VLOOKUP(Tabela1[[#This Row],[Cliente]],'BASE DE CLIENTES'!A:E,5,0) -> SETOR HABITACIONAL VICENTE PIRES
A37: 3672 | B37: 34.505.918 JOSE ANTONIO DUTRA DA SILVA | C37: =VLOOKUP(Tabela1[[#This Row],[Cliente]],'BASE DE CLIENTES'!A:E,2,0) -> Brasília | D37: =VLOOKUP(Tabela1[[#This Row],[Cliente]],'BASE DE CLIENTES'!A:C,3,0) -> DF | E37: =CONCATENATE(Tabela1[[#This Row],[CIDADE]],",",Tabela1[[#This Row],[UF]]) -> Brasília,DF | F37: 45686 | G37: 50 | H37: 60 | I37: =Tabela1[[#This Row],[Valor total]]-Tabela1[[#This Row],[Valor custo]] -> 10 | J37: =Tabela1[[#This Row],[MARGEM BRUTA]]/Tabela1[[#This Row],[Valor total]] -> 0.16666667 | K37: =VLOOKUP(Tabela1[[#This Row],[Cliente]],'BASE DE CLIENTES'!A:D,4,0) -> EMPRESA SEM MAQUINA | L37: =VLOOKUP(Tabela1[[#This Row],[Cliente]],'BASE DE CLIENTES'!A:E,5,0) -> RECANTO DAS EMAS
A38: 3671 | B38: 34.505.918 JOSE ANTONIO DUTRA DA SILVA | C38: =VLOOKUP(Tabela1[[#This Row],[Cliente]],'BASE DE CLIENTES'!A:E,2,0) -> Brasília | D38: =VLOOKUP(Tabela1[[#This Row],[Cliente]],'BASE DE CLIENTES'!A:C,3,0) -> DF | E38: =CONCATENATE(Tabela1[[#This Row],[CIDADE]],",",Tabela1[[#This Row],[UF]]) -> Brasília,DF | F38: 45686 | G38: 1736.13 | H38: 2300 | I38: =Tabela1[[#This Row],[Valor total]]-Tabela1[[#This Row],[Valor custo]] -> 563.87 | J38: =Tabela1[[#This Row],[MARGEM BRUTA]]/Tabela1[[#This Row],[Valor total]] -> 0.24516087 | K38: =VLOOKUP(Tabela1[[#This Row],[Cliente]],'BASE DE CLIENTES'!A:D,4,0) -> EMPRESA SEM MAQUINA | L38: =VLOOKUP(Tabela1[[#This Row],[Cliente]],'BASE DE CLIENTES'!A:E,5,0) -> RECANTO DAS EMAS
B39: MARIO APARECIDO PEREIRA DE BRITO | C39: =VLOOKUP(Tabela1[[#This Row],[Cliente]],'BASE DE CLIENTES'!A:E,2,0) -> Águas Lindas de Goiás | D39: =VLOOKUP(Tabela1[[#This Row],[Cliente]],'BASE DE CLIENTES'!A:C,3,0) -> GO | E39: =CONCATENATE(Tabela1[[#This Row],[CIDADE]],",",Tabela1[[#This Row],[UF]]) -> Águas Lindas de Goiás,GO | F39: 45667 | G39: 1106.09 | H39: 1750 | I39: =Tabela1[[#This Row],[Valor total]]-Tabela1[[#This Row],[Valor custo]] -> 643.91 | J39: =Tabela1[[#This Row],[MARGEM BRUTA]]/Tabela1[[#This Row],[Valor total]] -> 0.36794857 | K39: =VLOOKUP(Tabela1[[#This Row],[Cliente]],'BASE DE CLIENTES'!A:D,4,0) -> SERRALHEIRO | L39: =VLOOKUP(Tabela1[[#This Row],[Cliente]],'BASE DE CLIENTES'!A:E,5,0) -> Águas Lindas de Goiás
B40: Gefferson de Amorim | C40: =VLOOKUP(Tabela1[[#This Row],[Cliente]],'BASE DE CLIENTES'!A:E,2,0) -> Águas Lindas de Goiás | D40: =VLOOKUP(Tabela1[[#This Row],[Cliente]],'BASE DE CLIENTES'!A:C,3,0) -> GO | E40: =CONCATENATE(Tabela1[[#This Row],[CIDADE]],",",Tabela1[[#This Row],[UF]]) -> Águas Lindas de Goiás,GO | F40: 45667 | G40: 1025.87 | H40: 1618 | I40: =Tabela1[[#This Row],[Valor total]]-Tabela1[[#This Row],[Valor custo]] -> 592.13 | J40: =Tabela1[[#This Row],[MARGEM BRUTA]]/Tabela1[[#This Row],[Valor total]] -> 0.36596415 | K40: =VLOOKUP(Tabela1[[#This Row],[Cliente]],'BASE DE CLIENTES'!A:D,4,0) -> SERRALHEIRO | L40: =VLOOKUP(Tabela1[[#This Row],[Cliente]],'BASE DE CLIENTES'!A:E,5,0) -> Águas Lindas de Goiás
B41: MARIO APARECIDO PEREIRA DE BRITO | C41: =VLOOKUP(Tabela1[[#This Row],[Cliente]],'BASE DE CLIENTES'!A:E,2,0) -> Águas Lindas de Goiás | D41: =VLOOKUP(Tabela1[[#This Row],[Cliente]],'BASE DE CLIENTES'!A:C,3,0) -> GO | E41: =CONCATENATE(Tabela1[[#This Row],[CIDADE]],",",Tabela1[[#This Row],[UF]]) -> Águas Lindas de Goiás,GO | F41: 45666 | G41: 593.83 | H41: 945 | I41: =Tabela1[[#This Row],[Valor total]]-Tabela1[[#This Row],[Valor custo]] -> 351.17 | J41: =Tabela1[[#This Row],[MARGEM BRUTA]]/Tabela1[[#This Row],[Valor total]] -> 0.37160847 | K41: =VLOOKUP(Tabela1[[#This Row],[Cliente]],'BASE DE CLIENTES'!A:D,4,0) -> SERRALHEIRO | L41: =VLOOKUP(Tabela1[[#This Row],[Cliente]],'BASE DE CLIENTES'!A:E,5,0) -> Águas Lindas de Goiás
B42: MARIO APARECIDO PEREIRA DE BRITO | C42: =VLOOKUP(Tabela1[[#This Row],[Cliente]],'BASE DE CLIENTES'!A:E,2,0) -> Águas Lindas de Goiás | D42: =VLOOKUP(Tabela1[[#This Row],[Cliente]],'BASE DE CLIENTES'!A:C,3,0) -> GO | E42: =CONCATENATE(Tabela1[[#This Row],[CIDADE]],",",Tabela1[[#This Row],[UF]]) -> Águas Lindas de Goiás,GO | F42: 45664 | G42: 291 | H42: 375 | I42: =Tabela1[[#This Row],[Valor total]]-Tabela1[[#This Row],[Valor custo]] -> 84 | J42: =Tabela1[[#This Row],[MARGEM BRUTA]]/Tabela1[[#This Row],[Valor total]] -> 0.224 | K42: =VLOOKUP(Tabela1[[#This Row],[Cliente]],'BASE DE CLIENTES'!A:D,4,0) -> SERRALHEIRO | L42: =VLOOKUP(Tabela1[[#This Row],[Cliente]],'BASE DE CLIENTES'!A:E,5,0) -> Águas Lindas de Goiás
B43: AC COELHO MATERIAIS PARA CONSTRUCAO LTDA | C43: =VLOOKUP(Tabela1[[#This Row],[Cliente]],'BASE DE CLIENTES'!A:E,2,0) -> Brasília | D43: =VLOOKUP(Tabela1[[#This Row],[Cliente]],'BASE DE CLIENTES'!A:C,3,0) -> DF | E43: =CONCATENATE(Tabela1[[#This Row],[CIDADE]],",",Tabela1[[#This Row],[UF]]) -> Brasília,DF | F43: 45764 | G43: 4351.9 | H43: 8328 | I43: =Tabela1[[#This Row],[Valor total]]-Tabela1[[#This Row],[Valor custo]] -> 3976.1 | J43: =Tabela1[[#This Row],[MARGEM BRUTA]]/Tabela1[[#This Row],[Valor total]] -> 0.47743756 | K43: =VLOOKUP(Tabela1[[#This Row],[Cliente]],'BASE DE CLIENTES'!A:D,4,0) -> SEM CLASSIFICAÇÃO | L43: =VLOOKUP(Tabela1[[#This Row],[Cliente]],'BASE DE CLIENTES'!A:E,5,0) -> SETOR DE INDUSTRIA E ABASTECIMENTO
B44: CHAVEIRO MARCOS ÁGUAS CLARAS | C44: =VLOOKUP(Tabela1[[#This Row],[Cliente]],'BASE DE CLIENTES'!A:E,2,0) -> Brasília | D44: =VLOOKUP(Tabela1[[#This Row],[Cliente]],'BASE DE CLIENTES'!A:C,3,0) -> DF | E44: =CONCATENATE(Tabela1[[#This Row],[CIDADE]],",",Tabela1[[#This Row],[UF]]) -> Brasília,DF | F44: 45930 | G44: 293.13 | H44: 400 | I44: =Tabela1[[#This Row],[Valor total]]-Tabela1[[#This Row],[Valor custo]] -> 106.87 | J44: =Tabela1[[#This Row],[MARGEM BRUTA]]/Tabela1[[#This Row],[Valor total]] -> 0.267175 | K44: =VLOOKUP(Tabela1[[#This Row],[Cliente]],'BASE DE CLIENTES'!A:D,4,0) -> CHAVEIRO | L44: =VLOOKUP(Tabela1[[#This Row],[Cliente]],'BASE DE CLIENTES'!A:E,5,0) -> NA
A45: 3666 | B45: DILMAR PEREIRA DE SOUZA | C45: =VLOOKUP(Tabela1[[#This Row],[Cliente]],'BASE DE CLIENTES'!A:E,2,0) -> Brasília | D45: =VLOOKUP(Tabela1[[#This Row],[Cliente]],'BASE DE CLIENTES'!A:C,3,0) -> DF | E45: =CONCATENATE(Tabela1[[#This Row],[CIDADE]],",",Tabela1[[#This Row],[UF]]) -> Brasília,DF | F45: 45685 | G45: 5378.45 | H45: 8000 | I45: =Tabela1[[#This Row],[Valor total]]-Tabela1[[#This Row],[Valor custo]] -> 2621.55 | J45: =Tabela1[[#This Row],[MARGEM BRUTA]]/Tabela1[[#This Row],[Valor total]] -> 0.32769375 | K45: =VLOOKUP(Tabela1[[#This Row],[Cliente]],'BASE DE CLIENTES'!A:D,4,0) -> EMPRESA COM MAQUINA | L45: =VLOOKUP(Tabela1[[#This Row],[Cliente]],'BASE DE CLIENTES'!A:E,5,0) -> RIACHO FUNDO II
A46: 3663 | B46: 34.505.918 JOSE ANTONIO DUTRA DA SILVA | C46: =VLOOKUP(Tabela1[[#This Row],[Cliente]],'BASE DE CLIENTES'!A:E,2,0) -> Brasília | D46: =VLOOKUP(Tabela1[[#This Row],[Cliente]],'BASE DE CLIENTES'!A:C,3,0) -> DF | E46: =CONCATENATE(Tabela1[[#This Row],[CIDADE]],",",Tabela1[[#This Row],[UF]]) -> Brasília,DF | F46: 45685 | G46: 782.91 | H46: 1160 | I46: =Tabela1[[#This Row],[Valor total]]-Tabela1[[#This Row],[Valor custo]] -> 377.09 | J46: =Tabela1[[#This Row],[MARGEM BRUTA]]/Tabela1[[#This Row],[Valor total]] -> 0.32507759 | K46: =VLOOKUP(Tabela1[[#This Row],[Cliente]],'BASE DE CLIENTES'!A:D,4,0) -> EMPRESA SEM MAQUINA | L46: =VLOOKUP(Tabela1[[#This Row],[Cliente]],'BASE DE CLIENTES'!A:E,5,0) -> RECANTO DAS EMAS
A47: 3662 | B47: ACOFER METALURGICA E COMERCIO LTDA | C47: =VLOOKUP(Tabela1[[#This Row],[Cliente]],'BASE DE CLIENTES'!A:E,2,0) -> Brasília | D47: =VLOOKUP(Tabela1[[#This Row],[Cliente]],'BASE DE CLIENTES'!A:C,3,0) -> DF | E47: =CONCATENATE(Tabela1[[#This Row],[CIDADE]],",",Tabela1[[#This Row],[UF]]) -> Brasília,DF | F47: 45685 | G47: 593.83 | H47: 960 | I47: =Tabela1[[#This Row],[Valor total]]-Tabela1[[#This Row],[Valor custo]] -> 366.17 | J47: =Tabela1[[#This Row],[MARGEM BRUTA]]/Tabela1[[#This Row],[Valor total]] -> 0.38142708 | K47: =VLOOKUP(Tabela1[[#This Row],[Cliente]],'BASE DE CLIENTES'!A:D,4,0) -> EMPRESA SEM MAQUINA | L47: =VLOOKUP(Tabela1[[#This Row],[Cliente]],'BASE DE CLIENTES'!A:E,5,0) -> SETOR INDUSTRIAL (TAGUATINGA)
B48: M PORTAS AUTOMATICAS EIRELI | C48: =VLOOKUP(Tabela1[[#This Row],[Cliente]],'BASE DE CLIENTES'!A:E,2,0) -> Águas Lindas de Goiás | D48: =VLOOKUP(Tabela1[[#This Row],[Cliente]],'BASE DE CLIENTES'!A:C,3,0) -> GO | E48: =CONCATENATE(Tabela1[[#This Row],[CIDADE]],",",Tabela1[[#This Row],[UF]]) -> Águas Lindas de Goiás,GO | F48: 45661 | G48: 57.04 | H48: 89 | I48: =Tabela1[[#This Row],[Valor total]]-Tabela1[[#This Row],[Valor custo]] -> 31.96 | J48: =Tabela1[[#This Row],[MARGEM BRUTA]]/Tabela1[[#This Row],[Valor total]] -> 0.35910112 | K48: =VLOOKUP(Tabela1[[#This Row],[Cliente]],'BASE DE CLIENTES'!A:D,4,0) -> EMPRESA COM MAQUINA | L48: =VLOOKUP(Tabela1[[#This Row],[Cliente]],'BASE DE CLIENTES'!A:E,5,0) -> Águas Lindas de Goiás
B49: M PORTAS AUTOMATICAS EIRELI | C49: =VLOOKUP(Tabela1[[#This Row],[Cliente]],'BASE DE CLIENTES'!A:E,2,0) -> Águas Lindas de Goiás | D49: =VLOOKUP(Tabela1[[#This Row],[Cliente]],'BASE DE CLIENTES'!A:C,3,0) -> GO | E49: =CONCATENATE(Tabela1[[#This Row],[CIDADE]],",",Tabela1[[#This Row],[UF]]) -> Águas Lindas de Goiás,GO | F49: 45661 | G49: 540.99 | H49: 850 | I49: =Tabela1[[#This Row],[Valor total]]-Tabela1[[#This Row],[Valor custo]] -> 309.01 | J49: =Tabela1[[#This Row],[MARGEM BRUTA]]/Tabela1[[#This Row],[Valor total]] -> 0.36354118 | K49: =VLOOKUP(Tabela1[[#This Row],[Cliente]],'BASE DE CLIENTES'!A:D,4,0) -> EMPRESA COM MAQUINA | L49: =VLOOKUP(Tabela1[[#This Row],[Cliente]],'BASE DE CLIENTES'!A:E,5,0) -> Águas Lindas de Goiás
A50: 3659 | B50: TOTAL FORCE PORTAS DE ACO LTDA | C50: =VLOOKUP(Tabela1[[#This Row],[Cliente]],'BASE DE CLIENTES'!A:E,2,0) -> Brasília | D50: =VLOOKUP(Tabela1[[#This Row],[Cliente]],'BASE DE CLIENTES'!A:C,3,0) -> DF | E50: =CONCATENATE(Tabela1[[#This Row],[CIDADE]],",",Tabela1[[#This Row],[UF]]) -> Brasília,DF | F50: 45684 | G50: 4975.2 | H50: 6965 | I50: =Tabela1[[#This Row],[Valor total]]-Tabela1[[#This Row],[Valor custo]] -> 1989.8 | J50: =Tabela1[[#This Row],[MARGEM BRUTA]]/Tabela1[[#This Row],[Valor total]] -> 0.28568557 | K50: =VLOOKUP(Tabela1[[#This Row],[Cliente]],'BASE DE CLIENTES'!A:D,4,0) -> EMPRESA COM MAQUINA | L50: =VLOOKUP(Tabela1[[#This Row],[Cliente]],'BASE DE CLIENTES'!A:E,5,0) -> SAMAMBAIA SUL (SAMAMBAIA)
B51: M PORTAS AUTOMATICAS EIRELI | C51: =VLOOKUP(Tabela1[[#This Row],[Cliente]],'BASE DE CLIENTES'!A:E,2,0) -> Águas Lindas de Goiás | D51: =VLOOKUP(Tabela1[[#This Row],[Cliente]],'BASE DE CLIENTES'!A:C,3,0) -> GO | E51: =CONCATENATE(Tabela1[[#This Row],[CIDADE]],",",Tabela1[[#This Row],[UF]]) -> Águas Lindas de Goiás,GO | F51: 45659 | G51: 878.4 | H51: 1290 | I51: =Tabela1[[#This Row],[Valor total]]-Tabela1[[#This Row],[Valor custo]] -> 411.6 | J51: =Tabela1[[#This Row],[MARGEM BRUTA]]/Tabela1[[#This Row],[Valor total]] -> 0.31906977 | K51: =VLOOKUP(Tabela1[[#This Row],[Cliente]],'BASE DE CLIENTES'!A:D,4,0) -> EMPRESA COM MAQUINA | L51: =VLOOKUP(Tabela1[[#This Row],[Cliente]],'BASE DE CLIENTES'!A:E,5,0) -> Águas Lindas de Goiás
B52: MARIO APARECIDO PEREIRA DE BRITO | C52: =VLOOKUP(Tabela1[[#This Row],[Cliente]],'BASE DE CLIENTES'!A:E,2,0) -> Águas Lindas de Goiás | D52: =VLOOKUP(Tabela1[[#This Row],[Cliente]],'BASE DE CLIENTES'!A:C,3,0) -> GO | E52: =CONCATENATE(Tabela1[[#This Row],[CIDADE]],",",Tabela1[[#This Row],[UF]]) -> Águas Lindas de Goiás,GO | F52: 45659 | G52: 230 | H52: 460 | I52: =Tabela1[[#This Row],[Valor total]]-Tabela1[[#This Row],[Valor custo]] -> 230 | J52: =Tabela1[[#This Row],[MARGEM BRUTA]]/Tabela1[[#This Row],[Valor total]] -> 0.5 | K52: =VLOOKUP(Tabela1[[#This Row],[Cliente]],'BASE DE CLIENTES'!A:D,4,0) -> SERRALHEIRO | L52: =VLOOKUP(Tabela1[[#This Row],[Cliente]],'BASE DE CLIENTES'!A:E,5,0) -> Águas Lindas de Goiás
B53: M PORTAS AUTOMATICAS EIRELI | C53: =VLOOKUP(Tabela1[[#This Row],[Cliente]],'BASE DE CLIENTES'!A:E,2,0) -> Águas Lindas de Goiás | D53: =VLOOKUP(Tabela1[[#This Row],[Cliente]],'BASE DE CLIENTES'!A:C,3,0) -> GO | E53: =CONCATENATE(Tabela1[[#This Row],[CIDADE]],",",Tabela1[[#This Row],[UF]]) -> Águas Lindas de Goiás,GO | F53: 45716 | G53: 300 | H53: 840 | I53: =Tabela1[[#This Row],[Valor total]]-Tabela1[[#This Row],[Valor custo]] -> 540 | J53: =Tabela1[[#This Row],[MARGEM BRUTA]]/Tabela1[[#This Row],[Valor total]] -> 0.64285714 | K53: =VLOOKUP(Tabela1[[#This Row],[Cliente]],'BASE DE CLIENTES'!A:D,4,0) -> EMPRESA COM MAQUINA | L53: =VLOOKUP(Tabela1[[#This Row],[Cliente]],'BASE DE CLIENTES'!A:E,5,0) -> Águas Lindas de Goiás
A54: 3654 | B54: 44.601.860 LUIS HENRIQUE SOUZA DA SILVA | C54: =VLOOKUP(Tabela1[[#This Row],[Cliente]],'BASE DE CLIENTES'!A:E,2,0) -> Brasília | D54: =VLOOKUP(Tabela1[[#This Row],[Cliente]],'BASE DE CLIENTES'!A:C,3,0) -> DF | E54: =CONCATENATE(Tabela1[[#This Row],[CIDADE]],",",Tabela1[[#This Row],[UF]]) -> Brasília,DF | F54: 45684 | G54: 878.4 | H54: 1290 | I54: =Tabela1[[#This Row],[Valor total]]-Tabela1[[#This Row],[Valor custo]] -> 411.6 | J54: =Tabela1[[#This Row],[MARGEM BRUTA]]/Tabela1[[#This Row],[Valor total]] -> 0.31906977 | K54: =VLOOKUP(Tabela1[[#This Row],[Cliente]],'BASE DE CLIENTES'!A:D,4,0) -> EMPRESA COM MAQUINA | L54: =VLOOKUP(Tabela1[[#This Row],[Cliente]],'BASE DE CLIENTES'!A:E,5,0) -> TAGUATINGA NORTE (TAGUATINGA)
A55: 3653 | B55: 34.505.918 JOSE ANTONIO DUTRA DA SILVA | C55: =VLOOKUP(Tabela1[[#This Row],[Cliente]],'BASE DE CLIENTES'!A:E,2,0) -> Brasília | D55: =VLOOKUP(Tabela1[[#This Row],[Cliente]],'BASE DE CLIENTES'!A:C,3,0) -> DF | E55: =CONCATENATE(Tabela1[[#This Row],[CIDADE]],",",Tabela1[[#This Row],[UF]]) -> Brasília,DF | F55: 45684 | G55: 68.45 | H55: 450 | I55: =Tabela1[[#This Row],[Valor total]]-Tabela1[[#This Row],[Valor custo]] -> 381.55 | J55: =Tabela1[[#This Row],[MARGEM BRUTA]]/Tabela1[[#This Row],[Valor total]] -> 0.84788889 | K55: =VLOOKUP(Tabela1[[#This Row],[Cliente]],'BASE DE CLIENTES'!A:D,4,0) -> EMPRESA SEM MAQUINA | L55: =VLOOKUP(Tabela1[[#This Row],[Cliente]],'BASE DE CLIENTES'!A:E,5,0) -> RECANTO DAS EMAS
A56: 3652 | B56: EDIVALDO FERNANDES DA SILVA 00098636138 | C56: =VLOOKUP(Tabela1[[#This Row],[Cliente]],'BASE DE CLIENTES'!A:E,2,0) -> Brasília | D56: =VLOOKUP(Tabela1[[#This Row],[Cliente]],'BASE DE CLIENTES'!A:C,3,0) -> DF | E56: =CONCATENATE(Tabela1[[#This Row],[CIDADE]],",",Tabela1[[#This Row],[UF]]) -> Brasília,DF | F56: 45684 | G56: 368.22 | H56: 510 | I56: =Tabela1[[#This Row],[Valor total]]-Tabela1[[#This Row],[Valor custo]] -> 141.78 | J56: =Tabela1[[#This Row],[MARGEM BRUTA]]/Tabela1[[#This Row],[Valor total]] -> 0.278 | K56: =VLOOKUP(Tabela1[[#This Row],[Cliente]],'BASE DE CLIENTES'!A:D,4,0) -> EMPRESA SEM MAQUINA | L56: =VLOOKUP(Tabela1[[#This Row],[Cliente]],'BASE DE CLIENTES'!A:E,5,0) -> PONTE ALTA NORTE (GAMA)
A57: 3651 | B57: CENTRAL PORTAS DE ACO AUTOMATICAS LTDA | C57: =VLOOKUP(Tabela1[[#This Row],[Cliente]],'BASE DE CLIENTES'!A:E,2,0) -> Brasília | D57: =VLOOKUP(Tabela1[[#This Row],[Cliente]],'BASE DE CLIENTES'!A:C,3,0) -> DF | E57: =CONCATENATE(Tabela1[[#This Row],[CIDADE]],",",Tabela1[[#This Row],[UF]]) -> Brasília,DF | F57: 45684 | G57: 953.65 | H57: 1365 | I57: =Tabela1[[#This Row],[Valor total]]-Tabela1[[#This Row],[Valor custo]] -> 411.35 | J57: =Tabela1[[#This Row],[MARGEM BRUTA]]/Tabela1[[#This Row],[Valor total]] -> 0.30135531 | K57: =VLOOKUP(Tabela1[[#This Row],[Cliente]],'BASE DE CLIENTES'!A:D,4,0) -> EMPRESA COM MAQUINA | L57: =VLOOKUP(Tabela1[[#This Row],[Cliente]],'BASE DE CLIENTES'!A:E,5,0) -> CEILANDIA NORTE (CEILANDIA)
B58: M PORTAS AUTOMATICAS EIRELI | C58: =VLOOKUP(Tabela1[[#This Row],[Cliente]],'BASE DE CLIENTES'!A:E,2,0) -> Águas Lindas de Goiás | D58: =VLOOKUP(Tabela1[[#This Row],[Cliente]],'BASE DE CLIENTES'!A:C,3,0) -> GO | E58: =CONCATENATE(Tabela1[[#This Row],[CIDADE]],",",Tabela1[[#This Row],[UF]]) -> Águas Lindas de Goiás,GO | F58: 45715 | G58: 1317.6 | H58: 1935 | I58: =Tabela1[[#This Row],[Valor total]]-Tabela1[[#This Row],[Valor custo]] -> 617.4 | J58: =Tabela1[[#This Row],[MARGEM BRUTA]]/Tabela1[[#This Row],[Valor total]] -> 0.31906977 | K58: =VLOOKUP(Tabela1[[#This Row],[Cliente]],'BASE DE CLIENTES'!A:D,4,0) -> EMPRESA COM MAQUINA | L58: =VLOOKUP(Tabela1[[#This Row],[Cliente]],'BASE DE CLIENTES'!A:E,5,0) -> Águas Lindas de Goiás
A59: 3649 | B59: 34.505.918 JOSE ANTONIO DUTRA DA SILVA | C59: =VLOOKUP(Tabela1[[#This Row],[Cliente]],'BASE DE CLIENTES'!A:E,2,0) -> Brasília | D59: =VLOOKUP(Tabela1[[#This Row],[Cliente]],'BASE DE CLIENTES'!A:C,3,0) -> DF | E59: =CONCATENATE(Tabela1[[#This Row],[CIDADE]],",",Tabela1[[#This Row],[UF]]) -> Brasília,DF | F59: 45681 | G59: 1468.1 | H59: 2085 | I59: =Tabela1[[#This Row],[Valor total]]-Tabela1[[#This Row],[Valor custo]] -> 616.9 | J59: =Tabela1[[#This Row],[MARGEM BRUTA]]/Tabela1[[#This Row],[Valor total]] -> 0.2958753 | K59: =VLOOKUP(Tabela1[[#This Row],[Cliente]],'BASE DE CLIENTES'!A:D,4,0) -> EMPRESA SEM MAQUINA | L59: =VLOOKUP(Tabela1[[#This Row],[Cliente]],'BASE DE CLIENTES'!A:E,5,0) -> RECANTO DAS EMAS
A60: 3648 | B60: PORTAS AUTOMATICAS ARTE MANIA LTDA | C60: =VLOOKUP(Tabela1[[#This Row],[Cliente]],'BASE DE CLIENTES'!A:E,2,0) -> Brasília | D60: =VLOOKUP(Tabela1[[#This Row],[Cliente]],'BASE DE CLIENTES'!A:C,3,0) -> DF | E60: =CONCATENATE(Tabela1[[#This Row],[CIDADE]],",",Tabela1[[#This Row],[UF]]) -> Brasília,DF | F60: 45681 | G60: 4392 | H60: 5800 | I60: =Tabela1[[#This Row],[Valor total]]-Tabela1[[#This Row],[Valor custo]] -> 1408 | J60: =Tabela1[[#This Row],[MARGEM BRUTA]]/Tabela1[[#This Row],[Valor total]] -> 0.24275862 | K60: =VLOOKUP(Tabela1[[#This Row],[Cliente]],'BASE DE CLIENTES'!A:D,4,0) -> EMPRESA COM MAQUINA | L60: =VLOOKUP(Tabela1[[#This Row],[Cliente]],'BASE DE CLIENTES'!A:E,5,0) -> Setor Placa da Mercedes (Núcleo Bandeirante)
A61: 3647 | B61: JC portas | C61: =VLOOKUP(Tabela1[[#This Row],[Cliente]],'BASE DE CLIENTES'!A:E,2,0) -> Brasília | D61: =VLOOKUP(Tabela1[[#This Row],[Cliente]],'BASE DE CLIENTES'!A:C,3,0) -> DF | E61: =CONCATENATE(Tabela1[[#This Row],[CIDADE]],",",Tabela1[[#This Row],[UF]]) -> Brasília,DF | F61: 45681 | G61: 1472.23 | H61: 2235 | I61: =Tabela1[[#This Row],[Valor total]]-Tabela1[[#This Row],[Valor custo]] -> 762.77 | J61: =Tabela1[[#This Row],[MARGEM BRUTA]]/Tabela1[[#This Row],[Valor total]] -> 0.34128412 | K61: =VLOOKUP(Tabela1[[#This Row],[Cliente]],'BASE DE CLIENTES'!A:D,4,0) -> SERRALHEIRO | L61: =VLOOKUP(Tabela1[[#This Row],[Cliente]],'BASE DE CLIENTES'!A:E,5,0) -> Vila do Boa (São Sebastião)
A62: 3646 | B62: Jaime DF portas | C62: =VLOOKUP(Tabela1[[#This Row],[Cliente]],'BASE DE CLIENTES'!A:E,2,0) -> Brasília | D62: =VLOOKUP(Tabela1[[#This Row],[Cliente]],'BASE DE CLIENTES'!A:C,3,0) -> DF | E62: =CONCATENATE(Tabela1[[#This Row],[CIDADE]],",",Tabela1[[#This Row],[UF]]) -> Brasília,DF | F62: 45681 | G62: 183 | H62: 445 | I62: =Tabela1[[#This Row],[Valor total]]-Tabela1[[#This Row],[Valor custo]] -> 262 | J62: =Tabela1[[#This Row],[MARGEM BRUTA]]/Tabela1[[#This Row],[Valor total]] -> 0.58876404 | K62: =VLOOKUP(Tabela1[[#This Row],[Cliente]],'BASE DE CLIENTES'!A:D,4,0) -> EMPRESA SEM MAQUINA | L62: =VLOOKUP(Tabela1[[#This Row],[Cliente]],'BASE DE CLIENTES'!A:E,5,0) -> JOKEY
B63: EMERSON BARBOSA MUNIZ | C63: =VLOOKUP(Tabela1[[#This Row],[Cliente]],'BASE DE CLIENTES'!A:E,2,0) -> Águas Lindas de Goiás | D63: =VLOOKUP(Tabela1[[#This Row],[Cliente]],'BASE DE CLIENTES'!A:C,3,0) -> GO | E63: =CONCATENATE(Tabela1[[#This Row],[CIDADE]],",",Tabela1[[#This Row],[UF]]) -> Águas Lindas de Goiás,GO | F63: 45714 | G63: 878.4 | H63: 1280 | I63: =Tabela1[[#This Row],[Valor total]]-Tabela1[[#This Row],[Valor custo]] -> 401.6 | J63: =Tabela1[[#This Row],[MARGEM BRUTA]]/Tabela1[[#This Row],[Valor total]] -> 0.31375 | K63: =VLOOKUP(Tabela1[[#This Row],[Cliente]],'BASE DE CLIENTES'!A:D,4,0) -> SEM CLASSIFICAÇÃO | L63: =VLOOKUP(Tabela1[[#This Row],[Cliente]],'BASE DE CLIENTES'!A:E,5,0) -> Águas Lindas de Goiás
B64: M PORTAS AUTOMATICAS EIRELI | C64: =VLOOKUP(Tabela1[[#This Row],[Cliente]],'BASE DE CLIENTES'!A:E,2,0) -> Águas Lindas de Goiás | D64: =VLOOKUP(Tabela1[[#This Row],[Cliente]],'BASE DE CLIENTES'!A:C,3,0) -> GO | E64: =CONCATENATE(Tabela1[[#This Row],[CIDADE]],",",Tabela1[[#This Row],[UF]]) -> Águas Lindas de Goiás,GO | F64: 45714 | G64: 548.47 | H64: 195 | I64: =Tabela1[[#This Row],[Valor total]]-Tabela1[[#This Row],[Valor custo]] -> -353.47 | J64: =Tabela1[[#This Row],[MARGEM BRUTA]]/Tabela1[[#This Row],[Valor total]] -> -1.8126667 | K64: =VLOOKUP(Tabela1[[#This Row],[Cliente]],'BASE DE CLIENTES'!A:D,4,0) -> EMPRESA COM MAQUINA | L64: =VLOOKUP(Tabela1[[#This Row],[Cliente]],'BASE DE CLIENTES'!A:E,5,0) -> Águas Lindas de Goiás
A65: 3643 | B65: FRANCISCO VALDINAR PEREIRA DA SILVA 02490980327 | C65: =VLOOKUP(Tabela1[[#This Row],[Cliente]],'BASE DE CLIENTES'!A:E,2,0) -> Brasília | D65: =VLOOKUP(Tabela1[[#This Row],[Cliente]],'BASE DE CLIENTES'!A:C,3,0) -> DF | E65: =CONCATENATE(Tabela1[[#This Row],[CIDADE]],",",Tabela1[[#This Row],[UF]]) -> Brasília,DF | F65: 45681 | G65: 251 | H65: 280 | I65: =Tabela1[[#This Row],[Valor total]]-Tabela1[[#This Row],[Valor custo]] -> 29 | J65: =Tabela1[[#This Row],[MARGEM BRUTA]]/Tabela1[[#This Row],[Valor total]] -> 0.10357143 | K65: =VLOOKUP(Tabela1[[#This Row],[Cliente]],'BASE DE CLIENTES'!A:D,4,0) -> EMPRESA SEM MAQUINA | L65: =VLOOKUP(Tabela1[[#This Row],[Cliente]],'BASE DE CLIENTES'!A:E,5,0) -> RECANTO DAS EMAS
A66: 3642 | B66: 44.601.860 LUIS HENRIQUE SOUZA DA SILVA | C66: =VLOOKUP(Tabela1[[#This Row],[Cliente]],'BASE DE CLIENTES'!A:E,2,0) -> Brasília | D66: =VLOOKUP(Tabela1[[#This Row],[Cliente]],'BASE DE CLIENTES'!A:C,3,0) -> DF | E66: =CONCATENATE(Tabela1[[#This Row],[CIDADE]],",",Tabela1[[#This Row],[UF]]) -> Brasília,DF | F66: 45681 | G66: 531.45 | H66: 785 | I66: =Tabela1[[#This Row],[Valor total]]-Tabela1[[#This Row],[Valor custo]] -> 253.55 | J66: =Tabela1[[#This Row],[MARGEM BRUTA]]/Tabela1[[#This Row],[Valor total]] -> 0.32299363 | K66: =VLOOKUP(Tabela1[[#This Row],[Cliente]],'BASE DE CLIENTES'!A:D,4,0) -> EMPRESA COM MAQUINA | L66: =VLOOKUP(Tabela1[[#This Row],[Cliente]],'BASE DE CLIENTES'!A:E,5,0) -> TAGUATINGA NORTE (TAGUATINGA)
A67: 3641 | B67: 32.444.757 JOSE EUSEBIO RIBEIRO DE LIMA SILVA | C67: =VLOOKUP(Tabela1[[#This Row],[Cliente]],'BASE DE CLIENTES'!A:E,2,0) -> Brasília | D67: =VLOOKUP(Tabela1[[#This Row],[Cliente]],'BASE DE CLIENTES'!A:C,3,0) -> DF | E67: =CONCATENATE(Tabela1[[#This Row],[CIDADE]],",",Tabela1[[#This Row],[UF]]) -> Brasília,DF | F67: 45681 | G67: 268.46 | H67: 520 | I67: =Tabela1[[#This Row],[Valor total]]-Tabela1[[#This Row],[Valor custo]] -> 251.54 | J67: =Tabela1[[#This Row],[MARGEM BRUTA]]/Tabela1[[#This Row],[Valor total]] -> 0.48373077 | K67: =VLOOKUP(Tabela1[[#This Row],[Cliente]],'BASE DE CLIENTES'!A:D,4,0) -> SERRALHEIRO | L67: =VLOOKUP(Tabela1[[#This Row],[Cliente]],'BASE DE CLIENTES'!A:E,5,0) -> SAMAMBAIA NORTE (SAMAMBAIA)
A68: 3640 | B68: 34.505.918 JOSE ANTONIO DUTRA DA SILVA | C68: =VLOOKUP(Tabela1[[#This Row],[Cliente]],'BASE DE CLIENTES'!A:E,2,0) -> Brasília | D68: =VLOOKUP(Tabela1[[#This Row],[Cliente]],'BASE DE CLIENTES'!A:C,3,0) -> DF | E68: =CONCATENATE(Tabela1[[#This Row],[CIDADE]],",",Tabela1[[#This Row],[UF]]) -> Brasília,DF | F68: 45680 | G68: 150 | H68: 530 | I68: =Tabela1[[#This Row],[Valor total]]-Tabela1[[#This Row],[Valor custo]] -> 380 | J68: =Tabela1[[#This Row],[MARGEM BRUTA]]/Tabela1[[#This Row],[Valor total]] -> 0.71698113 | K68: =VLOOKUP(Tabela1[[#This Row],[Cliente]],'BASE DE CLIENTES'!A:D,4,0) -> EMPRESA SEM MAQUINA | L68: =VLOOKUP(Tabela1[[#This Row],[Cliente]],'BASE DE CLIENTES'!A:E,5,0) -> RECANTO DAS EMAS
B69: DILMAR PEREIRA DE SOUZA | C69: =VLOOKUP(Tabela1[[#This Row],[Cliente]],'BASE DE CLIENTES'!A:E,2,0) -> Brasília | D69: =VLOOKUP(Tabela1[[#This Row],[Cliente]],'BASE DE CLIENTES'!A:C,3,0) -> DF | E69: =CONCATENATE(Tabela1[[#This Row],[CIDADE]],",",Tabela1[[#This Row],[UF]]) -> Brasília,DF | F69: 45670 | G69: 5510.27 | H69: 7700 | I69: =Tabela1[[#This Row],[Valor total]]-Tabela1[[#This Row],[Valor custo]] -> 2189.73 | J69: =Tabela1[[#This Row],[MARGEM BRUTA]]/Tabela1[[#This Row],[Valor total]] -> 0.28438052 | K69: =VLOOKUP(Tabela1[[#This Row],[Cliente]],'BASE DE CLIENTES'!A:D,4,0) -> EMPRESA COM MAQUINA | L69: =VLOOKUP(Tabela1[[#This Row],[Cliente]],'BASE DE CLIENTES'!A:E,5,0) -> RIACHO FUNDO II
B70: DILMAR PEREIRA DE SOUZA | C70: =VLOOKUP(Tabela1[[#This Row],[Cliente]],'BASE DE CLIENTES'!A:E,2,0) -> Brasília | D70: =VLOOKUP(Tabela1[[#This Row],[Cliente]],'BASE DE CLIENTES'!A:C,3,0) -> DF | E70: =CONCATENATE(Tabela1[[#This Row],[CIDADE]],",",Tabela1[[#This Row],[UF]]) -> Brasília,DF | F70: 45692 | G70: 5258.76 | H70: 7000 | I70: =Tabela1[[#This Row],[Valor total]]-Tabela1[[#This Row],[Valor custo]] -> 1741.24 | J70: =Tabela1[[#This Row],[MARGEM BRUTA]]/Tabela1[[#This Row],[Valor total]] -> 0.24874857 | K70: =VLOOKUP(Tabela1[[#This Row],[Cliente]],'BASE DE CLIENTES'!A:D,4,0) -> EMPRESA COM MAQUINA | L70: =VLOOKUP(Tabela1[[#This Row],[Cliente]],'BASE DE CLIENTES'!A:E,5,0) -> RIACHO FUNDO II
B71: MARIO APARECIDO PEREIRA DE BRITO | C71: =VLOOKUP(Tabela1[[#This Row],[Cliente]],'BASE DE CLIENTES'!A:E,2,0) -> Águas Lindas de Goiás | D71: =VLOOKUP(Tabela1[[#This Row],[Cliente]],'BASE DE CLIENTES'!A:C,3,0) -> GO | E71: =CONCATENATE(Tabela1[[#This Row],[CIDADE]],",",Tabela1[[#This Row],[UF]]) -> Águas Lindas de Goiás,GO | F71: 45714 | G71: 472.2 | H71: 795 | I71: =Tabela1[[#This Row],[Valor total]]-Tabela1[[#This Row],[Valor custo]] -> 322.8 | J71: =Tabela1[[#This Row],[MARGEM BRUTA]]/Tabela1[[#This Row],[Valor total]] -> 0.40603774 | K71: =VLOOKUP(Tabela1[[#This Row],[Cliente]],'BASE DE CLIENTES'!A:D,4,0) -> SERRALHEIRO | L71: =VLOOKUP(Tabela1[[#This Row],[Cliente]],'BASE DE CLIENTES'!A:E,5,0) -> Águas Lindas de Goiás
A72: 3636 | B72: ROBSON VIEIRA KNUPP 00129041122 | C72: =VLOOKUP(Tabela1[[#This Row],[Cliente]],'BASE DE CLIENTES'!A:E,2,0) -> Brasília | D72: =VLOOKUP(Tabela1[[#This Row],[Cliente]],'BASE DE CLIENTES'!A:C,3,0) -> DF | E72: =CONCATENATE(Tabela1[[#This Row],[CIDADE]],",",Tabela1[[#This Row],[UF]]) -> Brasília,DF | F72: 45680 | G72: 5234.16 | H72: 7520 | I72: =Tabela1[[#This Row],[Valor total]]-Tabela1[[#This Row],[Valor custo]] -> 2285.84 | J72: =Tabela1[[#This Row],[MARGEM BRUTA]]/Tabela1[[#This Row],[Valor total]] -> 0.30396809 | K72: =VLOOKUP(Tabela1[[#This Row],[Cliente]],'BASE DE CLIENTES'!A:D,4,0) -> SERRALHEIRO | L72: =VLOOKUP(Tabela1[[#This Row],[Cliente]],'BASE DE CLIENTES'!A:E,5,0) -> RECANTO DAS EMAS
A73: 3634 | B73: CENTRAL PORTAS DE ACO AUTOMATICAS LTDA | C73: =VLOOKUP(Tabela1[[#This Row],[Cliente]],'BASE DE CLIENTES'!A:E,2,0) -> Brasília | D73: =VLOOKUP(Tabela1[[#This Row],[Cliente]],'BASE DE CLIENTES'!A:C,3,0) -> DF | E73: =CONCATENATE(Tabela1[[#This Row],[CIDADE]],",",Tabela1[[#This Row],[UF]]) -> Brasília,DF | F73: 45680 | G73: 1123.75 | H73: 1895 | I73: =Tabela1[[#This Row],[Valor total]]-Tabela1[[#This Row],[Valor custo]] -> 771.25 | J73: =Tabela1[[#This Row],[MARGEM BRUTA]]/Tabela1[[#This Row],[Valor total]] -> 0.40699208 | K73: =VLOOKUP(Tabela1[[#This Row],[Cliente]],'BASE DE CLIENTES'!A:D,4,0) -> EMPRESA COM MAQUINA | L73: =VLOOKUP(Tabela1[[#This Row],[Cliente]],'BASE DE CLIENTES'!A:E,5,0) -> CEILANDIA NORTE (CEILANDIA)
B74: CHAVEIRO MARCOS ÁGUAS CLARAS | C74: =VLOOKUP(Tabela1[[#This Row],[Cliente]],'BASE DE CLIENTES'!A:E,2,0) -> Brasília | D74: =VLOOKUP(Tabela1[[#This Row],[Cliente]],'BASE DE CLIENTES'!A:C,3,0) -> DF | E74: =CONCATENATE(Tabela1[[#This Row],[CIDADE]],",",Tabela1[[#This Row],[UF]]) -> Brasília,DF | F74: 45929 | G74: 586.26 | H74: 950 | I74: =Tabela1[[#This Row],[Valor total]]-Tabela1[[#This Row],[Valor custo]] -> 363.74 | J74: =Tabela1[[#This Row],[MARGEM BRUTA]]/Tabela1[[#This Row],[Valor total]] -> 0.38288421 | K74: =VLOOKUP(Tabela1[[#This Row],[Cliente]],'BASE DE CLIENTES'!A:D,4,0) -> CHAVEIRO | L74: =VLOOKUP(Tabela1[[#This Row],[Cliente]],'BASE DE CLIENTES'!A:E,5,0) -> NA
A75: 3632 | B75: JM PORTAS AUTOMATICAS LTDA | C75: =VLOOKUP(Tabela1[[#This Row],[Cliente]],'BASE DE CLIENTES'!A:E,2,0) -> Brasília | D75: =VLOOKUP(Tabela1[[#This Row],[Cliente]],'BASE DE CLIENTES'!A:C,3,0) -> DF | E75: =CONCATENATE(Tabela1[[#This Row],[CIDADE]],",",Tabela1[[#This Row],[UF]]) -> Brasília,DF | F75: 45680 | G75: 593.83 | H75: 945 | I75: =Tabela1[[#This Row],[Valor total]]-Tabela1[[#This Row],[Valor custo]] -> 351.17 | J75: =Tabela1[[#This Row],[MARGEM BRUTA]]/Tabela1[[#This Row],[Valor total]] -> 0.37160847 | K75: =VLOOKUP(Tabela1[[#This Row],[Cliente]],'BASE DE CLIENTES'!A:D,4,0) -> EMPRESA SEM MAQUINA | L75: =VLOOKUP(Tabela1[[#This Row],[Cliente]],'BASE DE CLIENTES'!A:E,5,0) -> SAMAMBAIA
B76: M PORTAS AUTOMATICAS EIRELI | C76: =VLOOKUP(Tabela1[[#This Row],[Cliente]],'BASE DE CLIENTES'!A:E,2,0) -> Águas Lindas de Goiás | D76: =VLOOKUP(Tabela1[[#This Row],[Cliente]],'BASE DE CLIENTES'!A:C,3,0) -> GO | E76: =CONCATENATE(Tabela1[[#This Row],[CIDADE]],",",Tabela1[[#This Row],[UF]]) -> Águas Lindas de Goiás,GO | F76: 45714 | G76: 529.2 | H76: 1045 | I76: =Tabela1[[#This Row],[Valor total]]-Tabela1[[#This Row],[Valor custo]] -> 515.8 | J76: =Tabela1[[#This Row],[MARGEM BRUTA]]/Tabela1[[#This Row],[Valor total]] -> 0.49358852 | K76: =VLOOKUP(Tabela1[[#This Row],[Cliente]],'BASE DE CLIENTES'!A:D,4,0) -> EMPRESA COM MAQUINA | L76: =VLOOKUP(Tabela1[[#This Row],[Cliente]],'BASE DE CLIENTES'!A:E,5,0) -> Águas Lindas de Goiás
A77: 3630 | B77: ATUAL PORTAS AUTOMATICAS FERRAGENS E ACESSORIOS LTDA | C77: =VLOOKUP(Tabela1[[#This Row],[Cliente]],'BASE DE CLIENTES'!A:E,2,0) -> Brasília | D77: =VLOOKUP(Tabela1[[#This Row],[Cliente]],'BASE DE CLIENTES'!A:C,3,0) -> DF | E77: =CONCATENATE(Tabela1[[#This Row],[CIDADE]],",",Tabela1[[#This Row],[UF]]) -> Brasília,DF | F77: 45679 | G77: 784.55 | H77: 1414.9 | I77: =Tabela1[[#This Row],[Valor total]]-Tabela1[[#This Row],[Valor custo]] -> 630.35 | J77: =Tabela1[[#This Row],[MARGEM BRUTA]]/Tabela1[[#This Row],[Valor total]] -> 0.44550852 | K77: =VLOOKUP(Tabela1[[#This Row],[Cliente]],'BASE DE CLIENTES'!A:D,4,0) -> EMPRESA SEM MAQUINA | L77: =VLOOKUP(Tabela1[[#This Row],[Cliente]],'BASE DE CLIENTES'!A:E,5,0) -> SOBRADINHO
B78: RONALDO ADRIANO DA SILVA SOLSA | C78: =VLOOKUP(Tabela1[[#This Row],[Cliente]],'BASE DE CLIENTES'!A:E,2,0) -> Águas Lindas de Goiás | D78: =VLOOKUP(Tabela1[[#This Row],[Cliente]],'BASE DE CLIENTES'!A:C,3,0) -> GO | E78: =CONCATENATE(Tabela1[[#This Row],[CIDADE]],",",Tabela1[[#This Row],[UF]]) -> Águas Lindas de Goiás,GO | F78: 45713 | G78: 100.64 | H78: 380 | I78: =Tabela1[[#This Row],[Valor total]]-Tabela1[[#This Row],[Valor custo]] -> 279.36 | J78: =Tabela1[[#This Row],[MARGEM BRUTA]]/Tabela1[[#This Row],[Valor total]] -> 0.73515789 | K78: =VLOOKUP(Tabela1[[#This Row],[Cliente]],'BASE DE CLIENTES'!A:D,4,0) -> SERRALHEIRO | L78: =VLOOKUP(Tabela1[[#This Row],[Cliente]],'BASE DE CLIENTES'!A:E,5,0) -> Águas Lindas de Goiás
A79: 3628 | B79: WILSON JOSE RODRIGUES JUNIOR 69748209172 | C79: =VLOOKUP(Tabela1[[#This Row],[Cliente]],'BASE DE CLIENTES'!A:E,2,0) -> Brasília | D79: =VLOOKUP(Tabela1[[#This Row],[Cliente]],'BASE DE CLIENTES'!A:C,3,0) -> DF | E79: =CONCATENATE(Tabela1[[#This Row],[CIDADE]],",",Tabela1[[#This Row],[UF]]) -> Brasília,DF | F79: 45679 | G79: 439.2 | H79: 645 | I79: =Tabela1[[#This Row],[Valor total]]-Tabela1[[#This Row],[Valor custo]] -> 205.8 | J79: =Tabela1[[#This Row],[MARGEM BRUTA]]/Tabela1[[#This Row],[Valor total]] -> 0.31906977 | K79: =VLOOKUP(Tabela1[[#This Row],[Cliente]],'BASE DE CLIENTES'!A:D,4,0) -> SERRALHEIRO | L79: =VLOOKUP(Tabela1[[#This Row],[Cliente]],'BASE DE CLIENTES'!A:E,5,0) -> CEILANDIA SUL (CEILANDIA)
B80: DILMAR PEREIRA DE SOUZA | C80: =VLOOKUP(Tabela1[[#This Row],[Cliente]],'BASE DE CLIENTES'!A:E,2,0) -> Brasília | D80: =VLOOKUP(Tabela1[[#This Row],[Cliente]],'BASE DE CLIENTES'!A:C,3,0) -> DF | E80: =CONCATENATE(Tabela1[[#This Row],[CIDADE]],",",Tabela1[[#This Row],[UF]]) -> Brasília,DF | F80: 45663 | G80: 4621.6 | H80: 6350 | I80: =Tabela1[[#This Row],[Valor total]]-Tabela1[[#This Row],[Valor custo]] -> 1728.4 | J80: =Tabela1[[#This Row],[MARGEM BRUTA]]/Tabela1[[#This Row],[Valor total]] -> 0.27218898 | K80: =VLOOKUP(Tabela1[[#This Row],[Cliente]],'BASE DE CLIENTES'!A:D,4,0) -> EMPRESA COM MAQUINA | L80: =VLOOKUP(Tabela1[[#This Row],[Cliente]],'BASE DE CLIENTES'!A:E,5,0) -> RIACHO FUNDO II
B81: MARIO APARECIDO PEREIRA DE BRITO | C81: =VLOOKUP(Tabela1[[#This Row],[Cliente]],'BASE DE CLIENTES'!A:E,2,0) -> Águas Lindas de Goiás | D81: =VLOOKUP(Tabela1[[#This Row],[Cliente]],'BASE DE CLIENTES'!A:C,3,0) -> GO | E81: =CONCATENATE(Tabela1[[#This Row],[CIDADE]],",",Tabela1[[#This Row],[UF]]) -> Águas Lindas de Goiás,GO | F81: 45713 | G81: 268.46 | H81: 550 | I81: =Tabela1[[#This Row],[Valor total]]-Tabela1[[#This Row],[Valor custo]] -> 281.54 | J81: =Tabela1[[#This Row],[MARGEM BRUTA]]/Tabela1[[#This Row],[Valor total]] -> 0.51189091 | K81: =VLOOKUP(Tabela1[[#This Row],[Cliente]],'BASE DE CLIENTES'!A:D,4,0) -> SERRALHEIRO | L81: =VLOOKUP(Tabela1[[#This Row],[Cliente]],'BASE DE CLIENTES'!A:E,5,0) -> Águas Lindas de Goiás
A82: 3624 | B82: Jaime DF portas | C82: =VLOOKUP(Tabela1[[#This Row],[Cliente]],'BASE DE CLIENTES'!A:E,2,0) -> Brasília | D82: =VLOOKUP(Tabela1[[#This Row],[Cliente]],'BASE DE CLIENTES'!A:C,3,0) -> DF | E82: =CONCATENATE(Tabela1[[#This Row],[CIDADE]],",",Tabela1[[#This Row],[UF]]) -> Brasília,DF | F82: 45679 | G82: 122.74 | H82: 170 | I82: =Tabela1[[#This Row],[Valor total]]-Tabela1[[#This Row],[Valor custo]] -> 47.26 | J82: =Tabela1[[#This Row],[MARGEM BRUTA]]/Tabela1[[#This Row],[Valor total]] -> 0.278 | K82: =VLOOKUP(Tabela1[[#This Row],[Cliente]],'BASE DE CLIENTES'!A:D,4,0) -> EMPRESA SEM MAQUINA | L82: =VLOOKUP(Tabela1[[#This Row],[Cliente]],'BASE DE CLIENTES'!A:E,5,0) -> JOKEY
B83: CHAVEIRO MARCOS ÁGUAS CLARAS | C83: =VLOOKUP(Tabela1[[#This Row],[Cliente]],'BASE DE CLIENTES'!A:E,2,0) -> Brasília | D83: =VLOOKUP(Tabela1[[#This Row],[Cliente]],'BASE DE CLIENTES'!A:C,3,0) -> DF | E83: =CONCATENATE(Tabela1[[#This Row],[CIDADE]],",",Tabela1[[#This Row],[UF]]) -> Brasília,DF | F83: 45924 | G83: 293.13 | H83: 370 | I83: =Tabela1[[#This Row],[Valor total]]-Tabela1[[#This Row],[Valor custo]] -> 76.87 | J83: =Tabela1[[#This Row],[MARGEM BRUTA]]/Tabela1[[#This Row],[Valor total]] -> 0.20775676 | K83: =VLOOKUP(Tabela1[[#This Row],[Cliente]],'BASE DE CLIENTES'!A:D,4,0) -> CHAVEIRO | L83: =VLOOKUP(Tabela1[[#This Row],[Cliente]],'BASE DE CLIENTES'!A:E,5,0) -> NA
A84: 3622 | B84: 32.444.757 JOSE EUSEBIO RIBEIRO DE LIMA SILVA | C84: =VLOOKUP(Tabela1[[#This Row],[Cliente]],'BASE DE CLIENTES'!A:E,2,0) -> Brasília | D84: =VLOOKUP(Tabela1[[#This Row],[Cliente]],'BASE DE CLIENTES'!A:C,3,0) -> DF | E84: =CONCATENATE(Tabela1[[#This Row],[CIDADE]],",",Tabela1[[#This Row],[UF]]) -> Brasília,DF | F84: 45679 | G84: 122.74 | H84: 180 | I84: =Tabela1[[#This Row],[Valor total]]-Tabela1[[#This Row],[Valor custo]] -> 57.26 | J84: =Tabela1[[#This Row],[MARGEM BRUTA]]/Tabela1[[#This Row],[Valor total]] -> 0.31811111 | K84: =VLOOKUP(Tabela1[[#This Row],[Cliente]],'BASE DE CLIENTES'!A:D,4,0) -> SERRALHEIRO | L84: =VLOOKUP(Tabela1[[#This Row],[Cliente]],'BASE DE CLIENTES'!A:E,5,0) -> SAMAMBAIA NORTE (SAMAMBAIA)
B85: M PORTAS AUTOMATICAS EIRELI | C85: =VLOOKUP(Tabela1[[#This Row],[Cliente]],'BASE DE CLIENTES'!A:E,2,0) -> Águas Lindas de Goiás | D85: =VLOOKUP(Tabela1[[#This Row],[Cliente]],'BASE DE CLIENTES'!A:C,3,0) -> GO | E85: =CONCATENATE(Tabela1[[#This Row],[CIDADE]],",",Tabela1[[#This Row],[UF]]) -> Águas Lindas de Goiás,GO | F85: 45712 | G85: 2196 | H85: 3200 | I85: =Tabela1[[#This Row],[Valor total]]-Tabela1[[#This Row],[Valor custo]] -> 1004 | J85: =Tabela1[[#This Row],[MARGEM BRUTA]]/Tabela1[[#This Row],[Valor total]] -> 0.31375 | K85: =VLOOKUP(Tabela1[[#This Row],[Cliente]],'BASE DE CLIENTES'!A:D,4,0) -> EMPRESA COM MAQUINA | L85: =VLOOKUP(Tabela1[[#This Row],[Cliente]],'BASE DE CLIENTES'!A:E,5,0) -> Águas Lindas de Goiás
B86: MRA - DISTRIBUIDORA DE PRODUTOS ELETRONICOS LTDA | C86: =VLOOKUP(Tabela1[[#This Row],[Cliente]],'BASE DE CLIENTES'!A:E,2,0) -> Brasília | D86: =VLOOKUP(Tabela1[[#This Row],[Cliente]],'BASE DE CLIENTES'!A:C,3,0) -> DF | E86: =CONCATENATE(Tabela1[[#This Row],[CIDADE]],",",Tabela1[[#This Row],[UF]]) -> Brasília,DF | F86: 45679 | G86: 593.83 | H86: 945 | I86: =Tabela1[[#This Row],[Valor total]]-Tabela1[[#This Row],[Valor custo]] -> 351.17 | J86: =Tabela1[[#This Row],[MARGEM BRUTA]]/Tabela1[[#This Row],[Valor total]] -> 0.37160847 | K86: =VLOOKUP(Tabela1[[#This Row],[Cliente]],'BASE DE CLIENTES'!A:D,4,0) -> EMPRESA SEM MAQUINA | L86: =VLOOKUP(Tabela1[[#This Row],[Cliente]],'BASE DE CLIENTES'!A:E,5,0) -> CEILANDIA NORTE (CEILANDIA)
B87: MARCELO DOS SANTOS 58472908100 | C87: =VLOOKUP(Tabela1[[#This Row],[Cliente]],'BASE DE CLIENTES'!A:E,2,0) -> Brasília | D87: =VLOOKUP(Tabela1[[#This Row],[Cliente]],'BASE DE CLIENTES'!A:C,3,0) -> DF | E87: =CONCATENATE(Tabela1[[#This Row],[CIDADE]],",",Tabela1[[#This Row],[UF]]) -> Brasília,DF | F87: 45679 | G87: 594.98 | H87: 878 | I87: =Tabela1[[#This Row],[Valor total]]-Tabela1[[#This Row],[Valor custo]] -> 283.02 | J87: =Tabela1[[#This Row],[MARGEM BRUTA]]/Tabela1[[#This Row],[Valor total]] -> 0.32234624 | K87: =VLOOKUP(Tabela1[[#This Row],[Cliente]],'BASE DE CLIENTES'!A:D,4,0) -> SERRALHEIRO | L87: =VLOOKUP(Tabela1[[#This Row],[Cliente]],'BASE DE CLIENTES'!A:E,5,0) -> CEILANDIA NORTE
B88: TOTAL FORCE PORTAS DE ACO LTDA | C88: =VLOOKUP(Tabela1[[#This Row],[Cliente]],'BASE DE CLIENTES'!A:E,2,0) -> Brasília | D88: =VLOOKUP(Tabela1[[#This Row],[Cliente]],'BASE DE CLIENTES'!A:C,3,0) -> DF | E88: =CONCATENATE(Tabela1[[#This Row],[CIDADE]],",",Tabela1[[#This Row],[UF]]) -> Brasília,DF | F88: 45679 | G88: 530.58 | H88: 645 | I88: =Tabela1[[#This Row],[Valor total]]-Tabela1[[#This Row],[Valor custo]] -> 114.42 | J88: =Tabela1[[#This Row],[MARGEM BRUTA]]/Tabela1[[#This Row],[Valor total]] -> 0.17739535 | K88: =VLOOKUP(Tabela1[[#This Row],[Cliente]],'BASE DE CLIENTES'!A:D,4,0) -> EMPRESA COM MAQUINA | L88: =VLOOKUP(Tabela1[[#This Row],[Cliente]],'BASE DE CLIENTES'!A:E,5,0) -> SAMAMBAIA SUL (SAMAMBAIA)
B89: DILMAR PEREIRA DE SOUZA | C89: =VLOOKUP(Tabela1[[#This Row],[Cliente]],'BASE DE CLIENTES'!A:E,2,0) -> Brasília | D89: =VLOOKUP(Tabela1[[#This Row],[Cliente]],'BASE DE CLIENTES'!A:C,3,0) -> DF | E89: =CONCATENATE(Tabela1[[#This Row],[CIDADE]],",",Tabela1[[#This Row],[UF]]) -> Brasília,DF | F89: 45742 | G89: 4098.7 | H89: 5850 | I89: =Tabela1[[#This Row],[Valor total]]-Tabela1[[#This Row],[Valor custo]] -> 1751.3 | J89: =Tabela1[[#This Row],[MARGEM BRUTA]]/Tabela1[[#This Row],[Valor total]] -> 0.29936752 | K89: =VLOOKUP(Tabela1[[#This Row],[Cliente]],'BASE DE CLIENTES'!A:D,4,0) -> EMPRESA COM MAQUINA | L89: =VLOOKUP(Tabela1[[#This Row],[Cliente]],'BASE DE CLIENTES'!A:E,5,0) -> RIACHO FUNDO II
B90: FRANCISCO VALDINAR PEREIRA DA SILVA 02490980327 | C90: =VLOOKUP(Tabela1[[#This Row],[Cliente]],'BASE DE CLIENTES'!A:E,2,0) -> Brasília | D90: =VLOOKUP(Tabela1[[#This Row],[Cliente]],'BASE DE CLIENTES'!A:C,3,0) -> DF | E90: =CONCATENATE(Tabela1[[#This Row],[CIDADE]],",",Tabela1[[#This Row],[UF]]) -> Brasília,DF | F90: 45678 | G90: 41 | H90: 75 | I90: =Tabela1[[#This Row],[Valor total]]-Tabela1[[#This Row],[Valor custo]] -> 34 | J90: =Tabela1[[#This Row],[MARGEM BRUTA]]/Tabela1[[#This Row],[Valor total]] -> 0.45333333 | K90: =VLOOKUP(Tabela1[[#This Row],[Cliente]],'BASE DE CLIENTES'!A:D,4,0) -> EMPRESA SEM MAQUINA | L90: =VLOOKUP(Tabela1[[#This Row],[Cliente]],'BASE DE CLIENTES'!A:E,5,0) -> RECANTO DAS EMAS
B91: Gefferson de Amorim | C91: =VLOOKUP(Tabela1[[#This Row],[Cliente]],'BASE DE CLIENTES'!A:E,2,0) -> Águas Lindas de Goiás | D91: =VLOOKUP(Tabela1[[#This Row],[Cliente]],'BASE DE CLIENTES'!A:C,3,0) -> GO | E91: =CONCATENATE(Tabela1[[#This Row],[CIDADE]],",",Tabela1[[#This Row],[UF]]) -> Águas Lindas de Goiás,GO | F91: 45709 | G91: 593.83 | H91: 900 | I91: =Tabela1[[#This Row],[Valor total]]-Tabela1[[#This Row],[Valor custo]] -> 306.17 | J91: =Tabela1[[#This Row],[MARGEM BRUTA]]/Tabela1[[#This Row],[Valor total]] -> 0.34018889 | K91: =VLOOKUP(Tabela1[[#This Row],[Cliente]],'BASE DE CLIENTES'!A:D,4,0) -> SERRALHEIRO | L91: =VLOOKUP(Tabela1[[#This Row],[Cliente]],'BASE DE CLIENTES'!A:E,5,0) -> Águas Lindas de Goiás
B92: 34.505.918 JOSE ANTONIO DUTRA DA SILVA | C92: =VLOOKUP(Tabela1[[#This Row],[Cliente]],'BASE DE CLIENTES'!A:E,2,0) -> Brasília | D92: =VLOOKUP(Tabela1[[#This Row],[Cliente]],'BASE DE CLIENTES'!A:C,3,0) -> DF | E92: =CONCATENATE(Tabela1[[#This Row],[CIDADE]],",",Tabela1[[#This Row],[UF]]) -> Brasília,DF | F92: 45678 | G92: 718.57 | H92: 1250 | I92: =Tabela1[[#This Row],[Valor total]]-Tabela1[[#This Row],[Valor custo]] -> 531.43 | J92: =Tabela1[[#This Row],[MARGEM BRUTA]]/Tabela1[[#This Row],[Valor total]] -> 0.425144 | K92: =VLOOKUP(Tabela1[[#This Row],[Cliente]],'BASE DE CLIENTES'!A:D,4,0) -> EMPRESA SEM MAQUINA | L92: =VLOOKUP(Tabela1[[#This Row],[Cliente]],'BASE DE CLIENTES'!A:E,5,0) -> RECANTO DAS EMAS
B93: NILO CELIO LIMA RIBEIRO 66545960130 | C93: =VLOOKUP(Tabela1[[#This Row],[Cliente]],'BASE DE CLIENTES'!A:E,2,0) -> Brasília | D93: =VLOOKUP(Tabela1[[#This Row],[Cliente]],'BASE DE CLIENTES'!A:C,3,0) -> DF | E93: =CONCATENATE(Tabela1[[#This Row],[CIDADE]],",",Tabela1[[#This Row],[UF]]) -> Brasília,DF | F93: 45678 | G93: 953.65 | H93: 1165 | I93: =Tabela1[[#This Row],[Valor total]]-Tabela1[[#This Row],[Valor custo]] -> 211.35 | J93: =Tabela1[[#This Row],[MARGEM BRUTA]]/Tabela1[[#This Row],[Valor total]] -> 0.18141631 | K93: =VLOOKUP(Tabela1[[#This Row],[Cliente]],'BASE DE CLIENTES'!A:D,4,0) -> SERRALHEIRO | L93: =VLOOKUP(Tabela1[[#This Row],[Cliente]],'BASE DE CLIENTES'!A:E,5,0) -> SANTA MARIA
B94: CHAVEIRO MARCOS ÁGUAS CLARAS | C94: =VLOOKUP(Tabela1[[#This Row],[Cliente]],'BASE DE CLIENTES'!A:E,2,0) -> Brasília | D94: =VLOOKUP(Tabela1[[#This Row],[Cliente]],'BASE DE CLIENTES'!A:C,3,0) -> DF | E94: =CONCATENATE(Tabela1[[#This Row],[CIDADE]],",",Tabela1[[#This Row],[UF]]) -> Brasília,DF | F94: 45903 | G94: 293.13 | H94: 500 | I94: =Tabela1[[#This Row],[Valor total]]-Tabela1[[#This Row],[Valor custo]] -> 206.87 | J94: =Tabela1[[#This Row],[MARGEM BRUTA]]/Tabela1[[#This Row],[Valor total]] -> 0.41374 | K94: =VLOOKUP(Tabela1[[#This Row],[Cliente]],'BASE DE CLIENTES'!A:D,4,0) -> CHAVEIRO | L94: =VLOOKUP(Tabela1[[#This Row],[Cliente]],'BASE DE CLIENTES'!A:E,5,0) -> NA
B95: CENTRAL PORTAS DE ACO AUTOMATICAS LTDA | C95: =VLOOKUP(Tabela1[[#This Row],[Cliente]],'BASE DE CLIENTES'!A:E,2,0) -> Brasília | D95: =VLOOKUP(Tabela1[[#This Row],[Cliente]],'BASE DE CLIENTES'!A:C,3,0) -> DF | E95: =CONCATENATE(Tabela1[[#This Row],[CIDADE]],",",Tabela1[[#This Row],[UF]]) -> Brasília,DF | F95: 45678 | G95: 2002.15 | H95: 3089.45 | I95: =Tabela1[[#This Row],[Valor total]]-Tabela1[[#This Row],[Valor custo]] -> 1087.3 | J95: =Tabela1[[#This Row],[MARGEM BRUTA]]/Tabela1[[#This Row],[Valor total]] -> 0.35193967 | K95: =VLOOKUP(Tabela1[[#This Row],[Cliente]],'BASE DE CLIENTES'!A:D,4,0) -> EMPRESA COM MAQUINA | L95: =VLOOKUP(Tabela1[[#This Row],[Cliente]],'BASE DE CLIENTES'!A:E,5,0) -> CEILANDIA NORTE (CEILANDIA)
B96: EMERSON BARBOSA MUNIZ | C96: =VLOOKUP(Tabela1[[#This Row],[Cliente]],'BASE DE CLIENTES'!A:E,2,0) -> Águas Lindas de Goiás | D96: =VLOOKUP(Tabela1[[#This Row],[Cliente]],'BASE DE CLIENTES'!A:C,3,0) -> GO | E96: =CONCATENATE(Tabela1[[#This Row],[CIDADE]],",",Tabela1[[#This Row],[UF]]) -> Águas Lindas de Goiás,GO | F96: 45708 | G96: 25 | H96: 30 | I96: =Tabela1[[#This Row],[Valor total]]-Tabela1[[#This Row],[Valor custo]] -> 5 | J96: =Tabela1[[#This Row],[MARGEM BRUTA]]/Tabela1[[#This Row],[Valor total]] -> 0.16666667 | K96: =VLOOKUP(Tabela1[[#This Row],[Cliente]],'BASE DE CLIENTES'!A:D,4,0) -> SEM CLASSIFICAÇÃO | L96: =VLOOKUP(Tabela1[[#This Row],[Cliente]],'BASE DE CLIENTES'!A:E,5,0) -> Águas Lindas de Goiás
... B114: M PORTAS AUTOMATICAS EIRELI | C114: =VLOOKUP(Tabela1[[#This Row],[Cliente]],'BASE DE CLIENTES'!A:E,2,0) -> Águas Lindas de Goiás | D114: =VLOOKUP(Tabela1[[#This Row],[Cliente]],'BASE DE CLIENTES'!A:C,3,0) -> GO | E114: =CONCATENATE(Tabela1[[#This Row],[CIDADE]],",",Tabela1[[#This Row],[UF]]) -> Águas Lindas de Goiás,GO | F114: 45744 | G114: 894 | H114: 1240 | I114: =Tabela1[[#This Row],[Valor total]]-Tabela1[[#This Row],[Valor custo]] -> 346 | J114: =Tabela1[[#This Row],[MARGEM BRUTA]]/Tabela1[[#This Row],[Valor total]] -> 0.27903226 | K114: =VLOOKUP(Tabela1[[#This Row],[Cliente]],'BASE DE CLIENTES'!A:D,4,0) -> EMPRESA COM MAQUINA | L114: =VLOOKUP(Tabela1[[#This Row],[Cliente]],'BASE DE CLIENTES'!A:E,5,0) -> Águas Lindas de Goiás
A115: 3703 | B115: DILMAR PEREIRA DE SOUZA | C115: =VLOOKUP(Tabela1[[#This Row],[Cliente]],'BASE DE CLIENTES'!A:E,2,0) -> Brasília | D115: =VLOOKUP(Tabela1[[#This Row],[Cliente]],'BASE DE CLIENTES'!A:C,3,0) -> DF | E115: =CONCATENATE(Tabela1[[#This Row],[CIDADE]],",",Tabela1[[#This Row],[UF]]) -> Brasília,DF | F115: 45688 | G115: 4118.7 | H115: 5832 | I115: =Tabela1[[#This Row],[Valor total]]-Tabela1[[#This Row],[Valor custo]] -> 1713.3 | J115: =Tabela1[[#This Row],[MARGEM BRUTA]]/Tabela1[[#This Row],[Valor total]] -> 0.29377572 | K115: =VLOOKUP(Tabela1[[#This Row],[Cliente]],'BASE DE CLIENTES'!A:D,4,0) -> EMPRESA COM MAQUINA | L115: =VLOOKUP(Tabela1[[#This Row],[Cliente]],'BASE DE CLIENTES'!A:E,5,0) -> RIACHO FUNDO II
B116: M PORTAS AUTOMATICAS EIRELI | C116: =VLOOKUP(Tabela1[[#This Row],[Cliente]],'BASE DE CLIENTES'!A:E,2,0) -> Águas Lindas de Goiás | D116: =VLOOKUP(Tabela1[[#This Row],[Cliente]],'BASE DE CLIENTES'!A:C,3,0) -> GO | E116: =CONCATENATE(Tabela1[[#This Row],[CIDADE]],",",Tabela1[[#This Row],[UF]]) -> Águas Lindas de Goiás,GO | F116: 45744 | G116: 1157 | H116: 1870 | I116: =Tabela1[[#This Row],[Valor total]]-Tabela1[[#This Row],[Valor custo]] -> 713 | J116: =Tabela1[[#This Row],[MARGEM BRUTA]]/Tabela1[[#This Row],[Valor total]] -> 0.38128342 | K116: =VLOOKUP(Tabela1[[#This Row],[Cliente]],'BASE DE CLIENTES'!A:D,4,0) -> EMPRESA COM MAQUINA | L116: =VLOOKUP(Tabela1[[#This Row],[Cliente]],'BASE DE CLIENTES'!A:E,5,0) -> Águas Lindas de Goiás
B117: MARIO APARECIDO PEREIRA DE BRITO | C117: =VLOOKUP(Tabela1[[#This Row],[Cliente]],'BASE DE CLIENTES'!A:E,2,0) -> Águas Lindas de Goiás | D117: =VLOOKUP(Tabela1[[#This Row],[Cliente]],'BASE DE CLIENTES'!A:C,3,0) -> GO | E117: =CONCATENATE(Tabela1[[#This Row],[CIDADE]],",",Tabela1[[#This Row],[UF]]) -> Águas Lindas de Goiás,GO | F117: 45744 | G117: 166 | H117: 200 | I117: =Tabela1[[#This Row],[Valor total]]-Tabela1[[#This Row],[Valor custo]] -> 34 | J117: =Tabela1[[#This Row],[MARGEM BRUTA]]/Tabela1[[#This Row],[Valor total]] -> 0.17 | K117: =VLOOKUP(Tabela1[[#This Row],[Cliente]],'BASE DE CLIENTES'!A:D,4,0) -> SERRALHEIRO | L117: =VLOOKUP(Tabela1[[#This Row],[Cliente]],'BASE DE CLIENTES'!A:E,5,0) -> Águas Lindas de Goiás
...

Sheet BASE DE PRODUTOS
A1: Cód. interno | B1: Cód. de barra | C1: Produto | D1: Quantidade | E1: Custo médio | F1: Custo total | G1: Valor médio | H1: Desconto | I1: Frete | J1: Valor total | K1: Lucro | L1: MÊS | M1: ANO
A2: 2014587755343 | B2: ------ | C2: BOBINA DE AÇO GALVANIZADA GI 0,70 X 136MM | D2: 5014 | E2: 6.93 | F2: 34747.02 | G2: 7.76 | H2: 55.68 | I2: 0 | J2: 38918.02 | K2: 4171 | L2: JANEIRO | M2: 2025
A3: 2098389351200 | B3: ------ | C3: PERFIL AUTOLUBRIFICANTE PVC | D3: 1350 | E3: 2.5 | F3: 3375 | G3: 3.07 | H3: 5.75 | I3: 83.02 | J3: 4139.77 | K3: 764.77 | L3: JANEIRO | M3: 2025
A4: 2033349347800 | B4: ------ | C4: TRAVA LAMINA PRETO DIREITO | D4: 325 | E4: 0.65 | F4: 211.25 | G4: 1.19 | H4: 2.88 | I4: 0 | J4: 387.12 | K4: 175.87 | L4: JANEIRO | M4: 2025
A5: 2006477461908 | B5: ------ | C5: TRAVA LAMINA ESQUERDO | D5: 325 | E5: 0.65 | F5: 211.25 | G5: 1.19 | H5: 2.88 | I5: 0 | J5: 387.12 | K5: 175.87 | L5: JANEIRO | M5: 2025
A6: 2096304900205 | B6: ------ | C6: KIT AC 200 | D6: 228 | E6: 439.2 | F6: 100137.6 | G6: 620.02 | H6: 493.63 | I6: 117.86 | J6: 141364.23 | K6: 41226.63 | L6: JANEIRO | M6: 2025
A7: 2050591800303 | B7: ------ | C7: KIT AC 300 | D7: 172 | E7: 514.45 | F7: 88485.4 | G7: 693.33 | H7: 621.03 | I7: 95.11 | J7: 119252.68 | K7: 30767.28 | L7: JANEIRO | M7: 2025
A8: 2083454607368 | B8: ------ | C8: CONTROLE ANALOGICO | D8: 159 | E8: 10.44 | F8: 1659.96 | G8: 31.03 | H8: 7.07 | I8: 129.22 | J8: 4933.09 | K8: 3273.13 | L8: JANEIRO | M8: 2025
A9: 2084280862006 | B9: ------ | C9: DISCO CORTE CORTG 7 POLEGADAS | D9: 100 | E9: 3.26 | F9: 326 | G9: 5 | H9: 0 | I9: 0 | J9: 500 | K9: 174 | L9: JANEIRO | M9: 2025
A10: 2033856541104 | B10: ------ | C10: DISCO CORTE CORTAG 4 POLEGADAS | D10: 100 | E10: 0.96 | F10: 96 | G10: 0.88 | H10: 0 | I10: 0 | J10: 87.5 | K10: -8.5 | L10: JANEIRO | M10: 2025
A11: 2027684638006 | B11: ------ | C11: KIT AC 400 | D11: 84 | E11: 531.45 | F11: 44641.8 | G11: 756.44 | H11: 233.09 | I11: 0 | J11: 63540.91 | K11: 18899.11 | L11: JANEIRO | M11: 2025
A12: 2089305209842 | B12: ------ | C12: ELETRODO 2,5 MM 350 MM 5KG | D12: 70 | E12: 12.55 | F12: 878.5 | G12: 13.71 | H12: 10 | I12: 0 | J12: 960 | K12: 81.5 | L12: JANEIRO | M12: 2025
A13: 2097826360003 | B13: ------ | C13: KIT AC 200 AUTOTREK | D13: 67 | E13: 409.87 | F13: 27461.29 | G13: 571.94 | H13: 0 | I13: 0 | J13: 38320 | K13: 10858.71 | L13: JANEIRO | M13: 2025
... A1027: 2095883960600 | B1027: ------ | C1027: CHICOTE DC | D1027: 1 | E1027: 0 | F1027: 0 | G1027: 50 | H1027: 0 | I1027: 0 | J1027: 50 | K1027: 50 | L1027: AGOSTO | M1027: 2026

Sheet BASE DE CLIENTES
A1: CLIENTE | B1: CIDADE | C1: UF | D1: CLASSIFICAÇÃO | E1: BAIRRO
A2: WERLES JOSE DA SILVA | B2: Brasília | C2: DF | D2: EMPRESA COM MAQUINA | E2: =VLOOKUP(A2,[1]relatorio_clientes!$C:$Q,15,0) -> 26 DE SETEMBRO
A3: M PORTAS AUTOMATICAS EIRELI | B3: Águas Lindas de Goiás | C3: GO | D3: EMPRESA COM MAQUINA | E3: =B3 -> Águas Lindas de Goiás
A4: MARIO APARECIDO PEREIRA DE BRITO | B4: Águas Lindas de Goiás | C4: GO | D4: SERRALHEIRO | E4: =B4 -> Águas Lindas de Goiás
A5: Gefferson de Amorim | B5: Águas Lindas de Goiás | C5: GO | D5: SERRALHEIRO | E5: =B5 -> Águas Lindas de Goiás
A6: JANILSON DE SOLSA SILVA | B6: Águas Lindas de Goiás | C6: GO | D6: SERRALHEIRO | E6: =B6 -> Águas Lindas de Goiás
A7: REBRASFARMA DROGARIAS LTDA | B7: Águas Lindas de Goiás | C7: GO | D7: SEM CLASSIFICAÇÃO | E7: =B7 -> Águas Lindas de Goiás
A8: EMERSON BARBOSA MUNIZ | B8: Águas Lindas de Goiás | C8: GO | D8: SEM CLASSIFICAÇÃO | E8: =B8 -> Águas Lindas de Goiás
A9: LOTERICA AGUAS LINDAS LTDA | B9: Águas Lindas de Goiás | C9: GO | D9: SEM CLASSIFICAÇÃO | E9: =B9 -> Águas Lindas de Goiás
A10: Orlando Dias Ribeiro | B10: Águas Lindas de Goiás | C10: GO | D10: SERRALHEIRO | E10: =B10 -> Águas Lindas de Goiás
A11: FERNANDES E MELO CONSTRUCOES LTDA | B11: Águas Lindas de Goiás | C11: GO | D11: EMPRESA SEM MAQUINA | E11: =B11 -> Águas Lindas de Goiás
A12: SERRALHERIA E METALUGICA DO GALEGO LTDA | B12: Águas Lindas de Goiás | C12: GO | D12: SERRALHEIRO | E12: =B12 -> Águas Lindas de Goiás
A13: RONALDO ADRIANO DA SILVA SOLSA | B13: Águas Lindas de Goiás | C13: GO | D13: SERRALHEIRO | E13: =B13 -> Águas Lindas de Goiás
A14: 53.840.528 TELMA REIS DE AMORIM MOUSINHO | B14: Águas Lindas de Goiás | C14: GO | D14: EMPRESA SEM MAQUINA | E14: =B14 -> Águas Lindas de Goiás
... A33: COMUNICAR SOCIEDADE COMERCIAL LTDA | B33: Brasilândia de Minas | C33: MG | D33: OUTROS RAMOS | E33: =B33 -> Brasilândia de Minas
A34: SERRALHERIA MORACHIK LTDA | B34: Brasília | C34: DF | D34: EMPRESA COM MAQUINA | E34: =VLOOKUP(A34,[1]relatorio_clientes!$C:$Q,15,0) -> ARAPOANGA (PLANALTINA)
A35: RAIMUNDO NONATO DA CUNHA 89072898168 | B35: Brasília | C35: DF | D35: SERRALHEIRO | E35: =VLOOKUP(A35,[1]relatorio_clientes!$C:$Q,15,0) -> ARAPOANGA (PLANALTINA)
A36: ANTONIO DO SANTOS RIBEIRO | B36: Águas Lindas de Goiás | C36: GO | D36: EMPRESA SEM MAQUINA | E36: =B36 -> Águas Lindas de Goiás
A37: IMPERIO PORTAS DE ACO LTDA | B37: Brasília | C37: DF | D37: EMPRESA COM MAQUINA | E37: ADE ÁGUAS CLARAS
A38: MHS EMPREENDIMENTOS - CONSTRUTORA E INCORPORADORA LTDA | B38: Brasília | C38: DF | D38: SEM CLASSIFICAÇÃO | E38: ADE ÁGUAS CLARAS
A39: LANTERNART LANTERNAGEM E PINTURA LTDA | B39: Brasília | C39: DF | D39: EMPRESA COM MAQUINA | E39: ADE CEILÂNDIA
A40: MV COMERCIO,IMPORTACAO & EXPORTACAO DE PRODUTOS ELETRONICOS LTDA | B40: Brasília | C40: DF | D40: PRODUTOS ELETRONICOS | E40: =VLOOKUP(A40,[1]relatorio_clientes!$C:$Q,15,0) -> AREAL (AGUAS CLARAS)
A41: EQUIP SOUND CAR LTDA | B41: Brasília | C41: DF | D41: SEM CLASSIFICAÇÃO | E41: =VLOOKUP(A41,[1]relatorio_clientes!$C:$Q,15,0) -> AREAL (AGUAS CLARAS)
A42: DG VOLTS ENGENHARIA E OBRAS LTDA | B42: Brasília | C42: DF | D42: SEM CLASSIFICAÇÃO | E42: =VLOOKUP(A42,[1]relatorio_clientes!$C:$Q,15,0) -> AREAL (AGUAS CLARAS)
A43: Agnaldo Evangelista Santos | B43: Brasília | C43: DF | D43: CHAVEIRO | E43: =VLOOKUP(A43,[1]relatorio_clientes!$B:$Q,16,0) -> Areal (Águas Claras)
A44: Santo grau | B44: Brasília | C44: DF | D44: CLIENTE FECHADURA | E44: =VLOOKUP(A44,[1]relatorio_clientes!$B:$Q,16,0) -> Areal (Águas Claras)
A45: ANDRADE E OLIVEIRA REPRESENTACOES | B45: Brasília | C45: DF | D45: SEM CLASSIFICAÇÃO | E45: =VLOOKUP(A45,[1]relatorio_clientes!$B:$Q,16,0) -> Areal (Águas Claras)
A46: GUSTAVO DOS SANTOS SILVA | B46: Brasília | C46: DF | D46: SEM CLASSIFICAÇÃO | E46: =VLOOKUP(A46,[1]relatorio_clientes!$B:$Q,16,0) -> Asa Norte
A47: AURORA BOREAL LUZ COMERCIO E IMPORTACAO LTDA | B47: Brasília | C47: DF | D47: SEM CLASSIFICAÇÃO | E47: =VLOOKUP(A47,[1]relatorio_clientes!$C:$Q,15,0) -> ASA NORTE
A48: PASTELARIA VICOSA LTDA | B48: Brasília | C48: DF | D48: SEM CLASSIFICAÇÃO | E48: =VLOOKUP(A48,[1]relatorio_clientes!$C:$Q,15,0) -> ASA NORTE
A49: DG ENGENHARIA E CONSTRUCOES LTDA | B49: Brasília | C49: DF | D49: SEM CLASSIFICAÇÃO | E49: =VLOOKUP(A49,[1]relatorio_clientes!$C:$Q,15,0) -> ASA SUL
A50: MELO CONSTUCOES E INTALACOES EIRELI-EPP | B50: Brasília | C50: DF | D50: SEM CLASSIFICAÇÃO | E50: =VLOOKUP(A50,[1]relatorio_clientes!$C:$Q,15,0) -> Asa Sul
A51: JK COMERCIO DE FERRAGENS LTDA | B51: Brasília | C51: DF | D51: SEM CLASSIFICAÇÃO | E51: =VLOOKUP(A51,[1]relatorio_clientes!$C:$Q,15,0) -> ASA SUL
A52: E L FRAGNAN SERRALHERIA E SERVICOS EIRELI | B52: Brasília | C52: DF | D52: EMPRESA COM MAQUINA | E52: =VLOOKUP(A52,[1]relatorio_clientes!$C:$Q,15,0) -> CANDANGOLANDIA
A53: SERRALHERIA MAYA LTDA | B53: Brasília | C53: DF | D53: SERRALHEIRO | E53: =VLOOKUP(A53,[1]relatorio_clientes!$C:$Q,15,0) -> CEILANDIA
A54: OTICA E RELOJOARIA VAZ LTDA | B54: Brasília | C54: DF | D54: SEM CLASSIFICAÇÃO | E54: =VLOOKUP(A54,[1]relatorio_clientes!$C:$Q,15,0) -> CEILANDIA
A55: MARCELO DOS SANTOS 58472908100 | B55: Brasília | C55: DF | D55: SERRALHEIRO | E55: =VLOOKUP(A55,[1]relatorio_clientes!$C:$Q,15,0) -> CEILANDIA NORTE
A56: RANGEL SILVA 02665458152 | B56: Brasília | C56: DF | D56: OUTROS RAMOS | E56: =VLOOKUP(A56,[1]relatorio_clientes!$C:$Q,15,0) -> CEILANDIA NORTE
A57: G2 EQUIPAMENTOS & SEGURANCA ELETRONICA LTDA | B57: Brasília | C57: DF | D57: OUTROS RAMOS | E57: =VLOOKUP(A57,[1]relatorio_clientes!$C:$Q,15,0) -> CEILANDIA NORTE (CEILANDIA)
A58: MRA - DISTRIBUIDORA DE PRODUTOS ELETRONICOS LTDA | B58: Brasília | C58: DF | D58: EMPRESA SEM MAQUINA | E58: =VLOOKUP(A58,[1]relatorio_clientes!$C:$Q,15,0) -> CEILANDIA NORTE (CEILANDIA)
... A60: LINEAR PORTAS LTDA | B60: Brasília | C60: DF | D60: EMPRESA SEM MAQUINA | E60: =VLOOKUP(A60,[1]relatorio_clientes!$C:$Q,15,0) -> CEILANDIA NORTE (CEILANDIA)
A61: Julio Gonçalves da Silva | B61: Brasília | C61: DF | D61: SEM CLASSIFICAÇÃO | E61: =VLOOKUP(A61,[1]relatorio_clientes!$B:$Q,16,0) -> Ceilândia Norte (Ceilândia)
A62: serralheria e barbosa | B62: Brasília | C62: DF | D62: SERRALHEIRO | E62: =VLOOKUP(A62,[1]relatorio_clientes!$B:$Q,16,0) -> Ceilândia Norte (Ceilândia)
A63: ROMÃO VITORINO DA SILVA | B63: Brasília | C63: DF | D63: SERRALHEIRO | E63: =VLOOKUP(A63,[1]relatorio_clientes!$B:$Q,16,0) -> Ceilândia Norte (Ceilândia)
A64: P. LAROSE INSTALACOES | B64: Brasília | C64: DF | D64: SERRALHEIRO | E64: =VLOOKUP(A64,[1]relatorio_clientes!$C:$Q,15,0) -> CEILANDIA SUL (CEILANDIA)
A65: WILSON JOSE RODRIGUES JUNIOR 69748209172 | B65: Brasília | C65: DF | D65: SERRALHEIRO | E65: =VLOOKUP(A65,[1]relatorio_clientes!$C:$Q,15,0) -> CEILANDIA SUL (CEILANDIA)
A66: CONFIANCIA SERRALHARIA LTDA | B66: Brasília | C66: DF | D66: EMPRESA COM MAQUINA | E66: =VLOOKUP(A66,[1]relatorio_clientes!$C:$Q,15,0) -> CEILANDIA SUL (CEILANDIA)
A67: FABIO BERNARDO DE ABREU | B67: Brasília | C67: DF | D67: SERRALHEIRO | E67: =VLOOKUP(A67,[1]relatorio_clientes!$B:$Q,16,0) -> Ceilândia Sul (Ceilândia)
A68: CAULITO XAVIER CUSTODIO | B68: Brasília | C68: DF | D68: SEM CLASSIFICAÇÃO | E68: =VLOOKUP(A68,[1]relatorio_clientes!$B:$Q,16,0) -> Ceilândia Sul (Ceilândia)
A69: TAGUAPORTAS - PORTAS DE ACO AUTOMATICA LTDA | B69: Brasília | C69: DF | D69: EMPRESA COM MAQUINA | E69: =VLOOKUP(A69,[1]relatorio_clientes!$C:$Q,15,0) -> FAZENDA MESTRE D'ARMAS (ETAPA I - PLANALTINA)
A70: CARLOS ALBERTO FLORENTINO MOTA 82180040172 | B70: Brasília | C70: DF | D70: SERRALHEIRO | E70: =VLOOKUP(A70,[1]relatorio_clientes!$C:$Q,15,0) -> FAZENDINHA (ITAPOA)
A71: Jaime DF portas | B71: Brasília | C71: DF | D71: EMPRESA SEM MAQUINA | E71: =VLOOKUP(A71,[1]relatorio_clientes!$B:$Q,16,0) -> JOKEY
A72: Carlos Alberto da Silva | B72: Brasília | C72: DF | D72: CLIENTE FECHADURA | E72: NA
A73: CHAVEIRO MARCOS ÁGUAS CLARAS | B73: Brasília | C73: DF | D73: CHAVEIRO | E73: NA
A74: Alberto Junio Romão Gonçalves | B74: Brasília | C74: DF | D74: EMPRESA SEM MAQUINA | E74: SAMAMBAIA
A75: Ana Claudia de Medeiros | B75: Brasília | C75: DF | D75: SEM CLASSIFICAÇÃO | E75: NA
A76: Jaime Francisco Godinho | B76: Brasília | C76: DF | D76: SEM CLASSIFICAÇÃO | E76: NA
A77: leandro serralheiro | B77: Brasília | C77: DF | D77: SERRALHEIRO | E77: NA
A78: Gean Claudio Gomes dos Santos | B78: Brasília | C78: DF | D78: SERRALHEIRO | E78: NA
A79: reunidas portas | B79: Brasília | C79: DF | D79: SEM CLASSIFICAÇÃO | E79: NA
A80: André Machado de Lima | B80: Brasília | C80: DF | D80: SEM CLASSIFICAÇÃO | E80: NA
A81: Romildo Francisco Dos Santos Silva | B81: Brasília | C81: DF | D81: SEM CLASSIFICAÇÃO | E81: NA
A82: Gesiel Da purificação Santos | B82: Brasília | C82: DF | D82: SEM CLASSIFICAÇÃO | E82: NA
A83: Douglas Souza | B83: Brasília | C83: DF | D83: SEM CLASSIFICAÇÃO | E83: NA
... A104: Augusto Fabiano Carvalho Codeceira | B104: Brasília | C104: DF | D104: CLIENTE FECHADURA | E104: ÁGUAS CLARAS
A105: LUCIANO SOUZA DA SILVA 09714565693 | B105: Brasília | C105: DF | D105: OUTROS RAMOS | E105: =VLOOKUP(A105,[1]relatorio_clientes!$C:$Q,15,0) -> PARANOA
A106: MONTEIRO FERRO E ACO LTDA | B106: Brasília | C106: DF | D106: EMPRESA COM MAQUINA | E106: =VLOOKUP(A106,[1]relatorio_clientes!$C:$Q,15,0) -> PLANALTINA
A107: P C DA COSTA SERRALHERIA | B107: Brasília | C107: DF | D107: SERRALHEIRO | E107: =VLOOKUP(A107,[1]relatorio_clientes!$C:$Q,15,0) -> PLANALTINA
A108: FABIO MOREIRA DE FREITAS | B108: Planaltina | C108: GO | D108: SERRALHEIRO | E108: =B108 -> Planaltina
A109: EDIVALDO FERNANDES DA SILVA 00098636138 | B109: Brasília | C109: DF | D109: EMPRESA SEM MAQUINA | E109: =VLOOKUP(A109,[1]relatorio_clientes!$C:$Q,15,0) -> PONTE ALTA NORTE (GAMA)
A110: CONEXAO COMERCIAL ATACADISTA DE MATERIAIS DE CONSTRUCAO LTDA | B110: Brasília | C110: DF | D110: SEM CLASSIFICAÇÃO | E110: =VLOOKUP(A110,[1]relatorio_clientes!$C:$Q,15,0) -> PONTE ALTA NORTE (GAMA)
A111: IARLA ANGÉLICA DO CARMO | B111: Brasília | C111: DF | D111: SEM CLASSIFICAÇÃO | E111: =VLOOKUP(A111,[1]relatorio_clientes!$B:$Q,16,0) -> Recanto das Emas
A112: Isaías Azevedo Silva | B112: Brasília | C112: DF | D112: SERRALHEIRO | E112: =VLOOKUP(A112,[1]relatorio_clientes!$B:$Q,16,0) -> Recanto das emas
A113: Marrone Gustavo Martins de Sousa | B113: Brasília | C113: DF | D113: SEM CLASSIFICAÇÃO | E113: =VLOOKUP(A113,[1]relatorio_clientes!$B:$Q,16,0) -> RECANTO DAS EMAS
A114: TF COMERCIO DE SOBREMESAS LTDA | B114: Brasília | C114: DF | D114: SEM CLASSIFICAÇÃO | E114: =VLOOKUP(A114,[1]relatorio_clientes!$C:$Q,15,0) -> RECANTO DAS EMAS
A115: SERRALHERIA VILMAR LTDA | B115: Brasília | C115: DF | D115: SERRALHEIRO | E115: =VLOOKUP(A115,[1]relatorio_clientes!$C:$Q,15,0) -> RECANTO DAS EMAS
A116: JULIO CESAR CIRILO DOS SANTOS 69973881168 | B116: Brasília | C116: DF | D116: SEM CLASSIFICAÇÃO | E116: =VLOOKUP(A116,[1]relatorio_clientes!$C:$Q,15,0) -> RECANTO DAS EMAS
A117: SERRALHERIA COMANDO PRESTACAO DE SERVICOS LTDA | B117: Brasília | C117: DF | D117: EMPRESA COM MAQUINA | E117: =VLOOKUP(A117,[1]relatorio_clientes!$C:$Q,15,0) -> RECANTO DAS EMAS
A118: 19.488.372 EZEQUIEL DE FREITAS CARNEIRO | B118: Brasília | C118: DF | D118: SERRALHEIRO | E118: =VLOOKUP(A118,[1]relatorio_clientes!$C:$Q,15,0) -> RECANTO DAS EMAS
A119: 34.505.918 JOSE ANTONIO DUTRA DA SILVA | B119: Brasília | C119: DF | D119: EMPRESA SEM MAQUINA | E119: =VLOOKUP(A119,[1]relatorio_clientes!$C:$Q,15,0) -> RECANTO DAS EMAS
A120: FRANCISCO VALDINAR PEREIRA DA SILVA 02490980327 | B120: Brasília | C120: DF | D120: EMPRESA SEM MAQUINA | E120: =VLOOKUP(A120,[1]relatorio_clientes!$C:$Q,15,0) -> RECANTO DAS EMAS
A121: ROBSON VIEIRA KNUPP 00129041122 | B121: Brasília | C121: DF | D121: SERRALHEIRO | E121: =VLOOKUP(A121,[1]relatorio_clientes!$C:$Q,15,0) -> RECANTO DAS EMAS
A122: Joyce Pimentel Barbosa Souza | B122: Brasília | C122: DF | D122: SEM CLASSIFICAÇÃO | E122: =VLOOKUP(A122,[1]relatorio_clientes!$B:$Q,16,0) -> Riacho Fundo I
A123: CLEVERSON PEREIRA COSTA 04013201119 | B123: Brasília | C123: DF | D123: SERRALHEIRO | E123: =VLOOKUP(A123,[1]relatorio_clientes!$C:$Q,15,0) -> RIACHO FUNDO I
A124: NEEMIAS VIEGAS COSTA 22073159168 | B124: Brasília | C124: DF | D124: EMPRESA COM MAQUINA | E124: =VLOOKUP(A124,[1]relatorio_clientes!$C:$Q,15,0) -> RIACHO FUNDO I
A125: I. L. P. RIBEIRO FERRAGENS E FERRAMENTAS | B125: Brasília | C125: DF | D125: SEM CLASSIFICAÇÃO | E125: =VLOOKUP(A125,[1]relatorio_clientes!$C:$Q,15,0) -> RIACHO FUNDO I
A126: 40.026.962 SAMUEL DE MATOS MELO | B126: Brasília | C126: DF | D126: SERRALHEIRO | E126: =VLOOKUP(A126,[1]relatorio_clientes!$C:$Q,15,0) -> RIACHO FUNDO I
A127: 60.775.634 WERNEI VIEGAS DA SILVA | B127: Brasília | C127: DF | D127: SERRALHEIRO | E127: =VLOOKUP(A127,[1]relatorio_clientes!$C:$Q,15,0) -> RIACHO FUNDO I
A128: RICARDO BARBOSA LEAL | B128: Brasília | C128: DF | D128: SEM CLASSIFICAÇÃO | E128: =VLOOKUP(A128,[1]relatorio_clientes!$B:$Q,16,0) -> Riacho Fundo II
A129: DILMAR PEREIRA DE SOUZA | B129: Brasília | C129: DF | D129: EMPRESA COM MAQUINA | E129: RIACHO FUNDO II
A130: JJ | B130: Brasília | C130: DF | D130: SERRALHEIRO | E130: =VLOOKUP(A130,[1]relatorio_clientes!$C:$Q,15,0) -> Riacho Fundo II
A131: J R CASTRO DA SILVA MANUTENCAO | B131: Brasília | C131: DF | D131: SERRALHEIRO | E131: =VLOOKUP(A131,[1]relatorio_clientes!$C:$Q,15,0) -> RIACHO FUNDO II
A132: 60.882.922 MARCOS REINAN LOPES | B132: Brasília | C132: DF | D132: EMPRESA COM MAQUINA | E132: =VLOOKUP(A132,[1]relatorio_clientes!$C:$Q,15,0) -> RIACHO FUNDO II
A133: PANIFICADORA E MERCEARIA ASSIS LTDA | B133: Brasília | C133: DF | D133: EMPRESA COM MAQUINA | E133: =VLOOKUP(A133,[1]relatorio_clientes!$C:$Q,15,0) -> RIACHO FUNDO II
A134: AUGUSTO CESAR OLIVEIRA DA SILVA 00732062101 | B134: Brasília | C134: DF | D134: OUTROS RAMOS | E134: =VLOOKUP(A134,[1]relatorio_clientes!$C:$Q,15,0) -> RIACHO FUNDO II
A135: BOM JESUS PORTAS AUTOMATICAS LTDA | B135: Brasília | C135: DF | D135: EMPRESA COM MAQUINA | E135: =VLOOKUP(A135,[1]relatorio_clientes!$C:$Q,15,0) -> RIACHO FUNDO II
A136: JM PORTAS AUTOMATICAS LTDA | B136: Brasília | C136: DF | D136: EMPRESA SEM MAQUINA | E136: =VLOOKUP(A136,[1]relatorio_clientes!$C:$Q,15,0) -> SAMAMBAIA
A137: TH MACHADO CONSTRUCOES LTDA | B137: Brasília | C137: DF | D137: SEM CLASSIFICAÇÃO | E137: =VLOOKUP(A137,[1]relatorio_clientes!$C:$Q,15,0) -> SAMAMBAIA NORTE
A138: wagner luis da silva bispo | B138: Brasília | C138: DF | D138: SEM CLASSIFICAÇÃO | E138: =VLOOKUP(A138,[1]relatorio_clientes!$B:$Q,16,0) -> Samambaia Norte (Samambaia)
A139: CELSO DA CRUZ PEREIRA | B139: Brasília | C139: DF | D139: SERRALHEIRO | E139: =VLOOKUP(A139,[1]relatorio_clientes!$B:$Q,16,0) -> Samambaia Norte (Samambaia)
...

Sheet LINHA
A1: PRODUTO | B1: CATEGORIA | C1: GRUPO | F1: CATEGORIA | G1: GRUPO
A2: AC 1000 | B2: MOTOR | C2: =VLOOKUP(B2,F:G,2,0) -> LINHA MOTOR | F2: MOTOR | G2: LINHA MOTOR
A3: AC 200 | B3: MOTOR | C3: =VLOOKUP(B3,F:G,2,0) -> LINHA MOTOR | F3: TESTEIRA | G3: LINHA MOTOR
A4: AC 200 AVULSO | B4: MOTOR | C4: =VLOOKUP(B4,F:G,2,0) -> LINHA MOTOR | F4: OUTROS | G4: OUTROS
A5: AC 300 | B5: MOTOR | C5: =VLOOKUP(B5,F:G,2,0) -> LINHA MOTOR | F5: NOBREAK | G5: LINHA MOTOR
A6: AC 400 | B6: MOTOR | C6: =VLOOKUP(B6,F:G,2,0) -> LINHA MOTOR | F6: BOBINA | G6: LINHA MOTOR
A7: AC 500 | B7: MOTOR | C7: =VLOOKUP(B7,F:G,2,0) -> LINHA MOTOR | F7: BOLACHA | G7: LINHA MOTOR
A8: AC 500 AVULSO | B8: MOTOR | C8: =VLOOKUP(B8,F:G,2,0) -> LINHA MOTOR | F8: SOLEIRA | G8: ACESSÓRIOS
A9: Anel da testeira | B9: TESTEIRA | C9: =VLOOKUP(B9,F:G,2,0) -> LINHA MOTOR | F9: BOTOEIRA | G9: LINHA MOTOR
A10: anel para testeira | B10: TESTEIRA | C10: =VLOOKUP(B10,F:G,2,0) -> LINHA MOTOR | F10: CAMISA | G10: OUTROS
A11: Anel proteção da corrente | B11: OUTROS | C11: =VLOOKUP(B11,F:G,2,0) -> OUTROS | F11: CENTRAL | G11: ACESSÓRIOS
A12: anti queda | B12: OUTROS | C12: =VLOOKUP(B12,F:G,2,0) -> OUTROS | F12: CAMISAS/BONÉS | G12: OUTROS
A13: BATERIA P/ NOBREAK | B13: NOBREAK | C13: =VLOOKUP(B13,F:G,2,0) -> LINHA MOTOR | F13: CONTROLE | G13: ACESSÓRIOS
... A45: CENTRAL WI-FI EVO | B45: CENTRAL | C45: =VLOOKUP(B45,F:G,2,0) -> ACESSÓRIOS | F45: CHICOTE | G45: LINHA MOTOR
A46: Chapeu | B46: CAMISAS/BONÉS | C46: =VLOOKUP(B46,F:G,2,0) -> OUTROS
A47: COMBO 01 CENTRAL WIFI, SENSOR DE ABERTURA E ANTIESMAGAMENTO | B47: CENTRAL | C47: =VLOOKUP(B47,F:G,2,0) -> ACESSÓRIOS
A48: COMBO 02 CENTRAL WIFI E SENSOR DE ABERTURA | B48: CENTRAL | C48: =VLOOKUP(B48,F:G,2,0) -> ACESSÓRIOS
A49: COMBO 03 CENTRAL WIFI E ANTIESMAGAMENTO | B49: CENTRAL | C49: =VLOOKUP(B49,F:G,2,0) -> ACESSÓRIOS
A50: CONTATO WI-FI MOTOR DE GARAGEM | B50: CENTRAL | C50: =VLOOKUP(B50,F:G,2,0) -> ACESSÓRIOS
A51: CONTROLE 8 CANAIS | B51: CONTROLE | C51: =VLOOKUP(B51,F:G,2,0) -> ACESSÓRIOS
A52: CONTROLE ANALOGICO | B52: CONTROLE | C52: =VLOOKUP(B52,F:G,2,0) -> ACESSÓRIOS
A53: controle copiador | B53: CONTROLE | C53: =VLOOKUP(B53,F:G,2,0) -> ACESSÓRIOS
A54: CONTROLE COPY EVO | B54: CONTROLE | C54: =VLOOKUP(B54,F:G,2,0) -> ACESSÓRIOS
A55: corrente | B55: CORRENTE | C55: =VLOOKUP(B55,F:G,2,0) -> LINHA MOTOR
A56: CORRENTE (TALHA) 3M | B56: CORRENTE | C56: =VLOOKUP(B56,F:G,2,0) -> LINHA MOTOR
A57: CORRENTE TESTEIRA | B57: TESTEIRA | C57: =VLOOKUP(B57,F:G,2,0) -> LINHA MOTOR
... A210: CENTRAL COPY/DIGITAL | B210: CENTRAL | C210: =VLOOKUP(B210,F:G,2,0) -> ACESSÓRIOS
